[
{"yr": "2002", "statcode": "102", "statkey": "2002102", "stat": "driving", "heading": "Driving Accuracy Percentage", "first": "81.24", "tenth": "75.59", "twentyfifth": "73.46", "hundredth": "67.81", "last": "50.37", "top10avg": "77.58", "top25avg": "75.79", "top100avg": "71.42"},
{"yr": "2002", "statcode": "077", "statkey": "2002077", "stat": "gir-100-125", "heading": "GIR Percentage - 100-125 yards", "first": "93.62", "tenth": "85.42", "twentyfifth": "81.13", "hundredth": "73.21", "last": "55.56", "top10avg": "87.94", "top25avg": "84.63", "top100avg": "78.99"},
{"yr": "2002", "statcode": "326", "statkey": "2002326", "stat": "gir-200-plus", "heading": "GIR Percentage - 200+ yards", "first": "76.47", "tenth": "57.14", "twentyfifth": "50.00", "hundredth": "35.71", "last": "5.88", "top10avg": "63.20", "top25avg": "57.11", "top100avg": "46.23"},
{"yr": "2002", "statcode": "419", "statkey": "2002419", "stat": "going-for-green", "heading": "Going for the Green", "first": "78.67", "tenth": "63.83", "twentyfifth": "58.75", "hundredth": "44.83", "last": "18.32", "top10avg": "69.73", "top25avg": "64.07", "top100avg": "53.36"},
{"yr": "2002", "statcode": "111", "statkey": "2002111", "stat": "sand-saves", "heading": "Sand Save Percentage", "first": "64.89", "tenth": "59.06", "twentyfifth": "56.47", "hundredth": "50.32", "last": "29.68", "top10avg": "60.68", "top25avg": "58.75", "top100avg": "54.68"},
{"yr": "2002", "statcode": "327", "statkey": "2002327", "stat": "gir-175-200", "heading": "GIR Percentage - 175-200 yards", "first": "77.08", "tenth": "66.07", "twentyfifth": "61.54", "hundredth": "52.94", "last": "31.43", "top10avg": "69.94", "top25avg": "66.26", "top100avg": "59.21"},
{"yr": "2002", "statcode": "328", "statkey": "2002328", "stat": "gir-150-175", "heading": "GIR Percentage - 150-175 yards", "first": "79.45", "tenth": "73.33", "twentyfifth": "69.57", "hundredth": "61.54", "last": "41.38", "top10avg": "75.51", "top25avg": "72.73", "top100avg": "67.15"},
{"yr": "2002", "statcode": "02437", "statkey": "200202437", "stat": "GOFIR", "heading": "Greens or Fringe in Regulation", "first": "108.26", "tenth": "101.20", "twentyfifth": "98.88", "hundredth": "93.71", "last": "81.73", "top10avg": "103.12", "top25avg": "101.21", "top100avg": "97.17"},
{"yr": "2002", "statcode": "103", "statkey": "2002103", "stat": "gir", "heading": "Greens in Regulation Percentage", "first": "73.96", "tenth": "70.18", "twentyfifth": "69.05", "hundredth": "65.65", "last": "57.03", "top10avg": "71.17", "top25avg": "70.09", "top100avg": "67.84"},
{"yr": "2002", "statcode": "329", "statkey": "2002329", "stat": "gir-125-150", "heading": "GIR Percentage - 125-150 yards", "first": "83.10", "tenth": "78.95", "twentyfifth": "76.85", "hundredth": "70.83", "last": "48.39", "top10avg": "80.78", "top25avg": "78.97", "top100avg": "74.87"},
{"yr": "2002", "statcode": "119", "statkey": "2002119", "stat": "putts-per-round", "heading": "Putts Per Round", "first": "27.57", "tenth": "28.32", "twentyfifth": "28.46", "hundredth": "29.00", "last": "30.45", "top10avg": "28.09", "top25avg": "28.29", "top100avg": "28.66"},
{"yr": "2002", "statcode": "400", "statkey": "2002400", "stat": "3-putts-per-round", "heading": "3-Putts per Round", "first": "1.00", "tenth": ".76", "twentyfifth": ".66", "hundredth": ".51", "last": ".26", "top10avg": "0.83", "top25avg": "0.75", "top100avg": "0.62"},
{"yr": "2002", "statcode": "364", "statkey": "2002364", "stat": "scrambling-from-fringe", "heading": "Scrambling from the Fringe", "first": "94.20", "tenth": "90.91", "twentyfifth": "88.54", "hundredth": "84.46", "last": "70.18", "top10avg": "92.09", "top25avg": "90.49", "top100avg": "87.43"},
{"yr": "2002", "statcode": "399", "statkey": "2002399", "stat": "2-putts-per-round", "heading": "2-Putts per Round", "first": "11.24", "tenth": "10.80", "twentyfifth": "10.56", "hundredth": "10.10", "last": "8.68", "top10avg": "10.97", "top25avg": "10.79", "top100avg": "10.41"},
{"yr": "2002", "statcode": "398", "statkey": "2002398", "stat": "1-putts-per-round", "heading": "1-Putts per Round", "first": "8.43", "tenth": "7.52", "twentyfifth": "7.35", "hundredth": "6.97", "last": "5.79", "top10avg": "7.74", "top25avg": "7.55", "top100avg": "7.24"},
{"yr": "2002", "statcode": "130", "statkey": "2002130", "stat": "scrambling", "heading": "Scrambling", "first": "69.67", "tenth": "64.58", "twentyfifth": "62.98", "hundredth": "59.59", "last": "47.08", "top10avg": "65.67", "top25avg": "64.38", "top100avg": "61.81"},
{"yr": "2003", "statcode": "102", "statkey": "2003102", "stat": "driving", "heading": "Driving Accuracy Percentage", "first": "77.86", "tenth": "73.95", "twentyfifth": "72.11", "hundredth": "66.82", "last": "48.02", "top10avg": "75.30", "top25avg": "73.92", "top100avg": "69.99"},
{"yr": "2002", "statcode": "403", "statkey": "2002403", "stat": "putting-inside-5", "heading": "Putting from Inside 5'", "first": "99.54", "tenth": "98.38", "twentyfifth": "97.89", "hundredth": "96.73", "last": "92.83", "top10avg": "98.77", "top25avg": "98.33", "top100avg": "97.52"},
{"yr": "2003", "statcode": "02437", "statkey": "200302437", "stat": "GOFIR", "heading": "Greens or Fringe in Regulation", "first": "106.03", "tenth": "101.79", "twentyfifth": "100.50", "hundredth": "96.31", "last": "87.44", "top10avg": "102.94", "top25avg": "101.82", "top100avg": "99.07"},
{"yr": "2002", "statcode": "484", "statkey": "2002484", "stat": "putting-inside-10", "heading": "Putting - Inside 10'", "first": "92.40", "tenth": "90.36", "twentyfifth": "89.66", "hundredth": "87.75", "last": "83.33", "top10avg": "90.98", "top25avg": "90.37", "top100avg": "89.05"},
{"yr": "2003", "statcode": "103", "statkey": "2003103", "stat": "gir", "heading": "Greens in Regulation Percentage", "first": "72.86", "tenth": "69.75", "twentyfifth": "68.75", "hundredth": "65.04", "last": "58.59", "top10avg": "70.89", "top25avg": "69.81", "top100avg": "67.62"},
{"yr": "2003", "statcode": "077", "statkey": "2003077", "stat": "gir-100-125", "heading": "GIR Percentage - 100-125 yards", "first": "86.92", "tenth": "81.54", "twentyfifth": "79.14", "hundredth": "73.68", "last": "59.09", "top10avg": "82.78", "top25avg": "81.22", "top100avg": "77.37"},
{"yr": "2003", "statcode": "328", "statkey": "2003328", "stat": "gir-150-175", "heading": "GIR Percentage - 150-175 yards", "first": "69.77", "tenth": "67.31", "twentyfifth": "64.88", "hundredth": "60.00", "last": "45.26", "top10avg": "68.36", "top25avg": "66.96", "top100avg": "63.34"},
{"yr": "2003", "statcode": "419", "statkey": "2003419", "stat": "going-for-green", "heading": "Going for the Green", "first": "77.17", "tenth": "67.25", "twentyfifth": "62.19", "hundredth": "51.50", "last": "21.33", "top10avg": "71.60", "top25avg": "67.05", "top100avg": "59.30"},
{"yr": "2003", "statcode": "327", "statkey": "2003327", "stat": "gir-175-200", "heading": "GIR Percentage - 175-200 yards", "first": "64.56", "tenth": "59.18", "twentyfifth": "54.95", "hundredth": "48.85", "last": "20.59", "top10avg": "62.08", "top25avg": "58.64", "top100avg": "53.16"},
{"yr": "2003", "statcode": "326", "statkey": "2003326", "stat": "gir-200-plus", "heading": "GIR Percentage - 200+ yards", "first": "55.56", "tenth": "47.50", "twentyfifth": "40.21", "hundredth": "30.00", "last": "11.76", "top10avg": "51.26", "top25avg": "45.93", "top100avg": "37.73"},
{"yr": "2003", "statcode": "329", "statkey": "2003329", "stat": "gir-125-150", "heading": "GIR Percentage - 125-150 yards", "first": "79.89", "tenth": "75.41", "twentyfifth": "73.45", "hundredth": "68.75", "last": "56.34", "top10avg": "77.05", "top25avg": "75.44", "top100avg": "72.16"},
{"yr": "2003", "statcode": "111", "statkey": "2003111", "stat": "sand-saves", "heading": "Sand Save Percentage", "first": "62.12", "tenth": "58.17", "twentyfifth": "55.56", "hundredth": "50.00", "last": "30.25", "top10avg": "59.48", "top25avg": "57.83", "top100avg": "53.73"},
{"yr": "2003", "statcode": "130", "statkey": "2003130", "stat": "scrambling", "heading": "Scrambling", "first": "67.28", "tenth": "63.10", "twentyfifth": "61.63", "hundredth": "58.00", "last": "47.86", "top10avg": "64.17", "top25avg": "62.93", "top100avg": "60.59"},
{"yr": "2003", "statcode": "364", "statkey": "2003364", "stat": "scrambling-from-fringe", "heading": "Scrambling from the Fringe", "first": "93.90", "tenth": "91.46", "twentyfifth": "89.15", "hundredth": "85.00", "last": "72.63", "top10avg": "92.85", "top25avg": "91.16", "top100avg": "88.03"},
{"yr": "2003", "statcode": "119", "statkey": "2003119", "stat": "putts-per-round", "heading": "Putts Per Round", "first": "27.88", "tenth": "28.34", "twentyfifth": "28.57", "hundredth": "29.16", "last": "30.30", "top10avg": "28.17", "top25avg": "28.36", "top100avg": "28.75"},
{"yr": "2003", "statcode": "400", "statkey": "2003400", "stat": "3-putts-per-round", "heading": "3-Putts per Round", "first": ".93", "tenth": ".80", "twentyfifth": ".71", "hundredth": ".54", "last": ".24", "top10avg": "0.85", "top25avg": "0.79", "top100avg": "0.66"},
{"yr": "2003", "statcode": "399", "statkey": "2003399", "stat": "2-putts-per-round", "heading": "2-Putts per Round", "first": "11.06", "tenth": "10.75", "twentyfifth": "10.55", "hundredth": "10.11", "last": "9.23", "top10avg": "10.89", "top25avg": "10.73", "top100avg": "10.39"},
{"yr": "2004", "statcode": "102", "statkey": "2004102", "stat": "driving", "heading": "Driving Accuracy Percentage", "first": "77.23", "tenth": "73.13", "twentyfifth": "69.92", "hundredth": "64.21", "last": "49.88", "top10avg": "74.88", "top25avg": "72.62", "top100avg": "68.15"},
{"yr": "2004", "statcode": "077", "statkey": "2004077", "stat": "gir-100-125", "heading": "GIR Percentage - 100-125 yards", "first": "83.33", "tenth": "81.82", "twentyfifth": "78.83", "hundredth": "73.14", "last": "60.77", "top10avg": "82.42", "top25avg": "81.10", "top100avg": "77.00"},
{"yr": "2004", "statcode": "328", "statkey": "2004328", "stat": "gir-150-175", "heading": "GIR Percentage - 150-175 yards", "first": "74.24", "tenth": "68.65", "twentyfifth": "67.28", "hundredth": "62.05", "last": "48.03", "top10avg": "70.65", "top25avg": "68.84", "top100avg": "65.23"},
{"yr": "2003", "statcode": "403", "statkey": "2003403", "stat": "putting-inside-5", "heading": "Putting from Inside 5'", "first": "98.48", "tenth": "97.80", "twentyfifth": "97.39", "hundredth": "96.60", "last": "94.07", "top10avg": "97.99", "top25avg": "97.73", "top100avg": "97.18"},
{"yr": "2003", "statcode": "484", "statkey": "2003484", "stat": "putting-inside-10", "heading": "Putting - Inside 10'", "first": "90.28", "tenth": "89.10", "twentyfifth": "88.68", "hundredth": "87.54", "last": "84.39", "top10avg": "89.50", "top25avg": "89.14", "top100avg": "88.31"},
{"yr": "2003", "statcode": "398", "statkey": "2003398", "stat": "1-putts-per-round", "heading": "1-Putts per Round", "first": "8.00", "tenth": "7.61", "twentyfifth": "7.37", "hundredth": "6.94", "last": "5.95", "top10avg": "7.72", "top25avg": "7.57", "top100avg": "7.23"},
{"yr": "2004", "statcode": "327", "statkey": "2004327", "stat": "gir-175-200", "heading": "GIR Percentage - 175-200 yards", "first": "66.20", "tenth": "61.40", "twentyfifth": "59.31", "hundredth": "54.02", "last": "33.14", "top10avg": "63.81", "top25avg": "61.57", "top100avg": "57.75"},
{"yr": "2004", "statcode": "103", "statkey": "2004103", "stat": "gir", "heading": "Greens in Regulation Percentage", "first": "73.27", "tenth": "69.55", "twentyfifth": "68.14", "hundredth": "64.92", "last": "54.68", "top10avg": "70.99", "top25avg": "69.60", "top100avg": "67.20"},
{"yr": "2004", "statcode": "02437", "statkey": "200402437", "stat": "GOFIR", "heading": "Greens or Fringe in Regulation", "first": "80.74", "tenth": "77.81", "twentyfifth": "76.20", "hundredth": "72.92", "last": "59.54", "top10avg": "78.92", "top25avg": "77.61", "top100avg": "75.18"},
{"yr": "2004", "statcode": "329", "statkey": "2004329", "stat": "gir-125-150", "heading": "GIR Percentage - 125-150 yards", "first": "78.76", "tenth": "75.51", "twentyfifth": "73.96", "hundredth": "69.41", "last": "60.61", "top10avg": "76.53", "top25avg": "75.37", "top100avg": "72.21"},
{"yr": "2004", "statcode": "326", "statkey": "2004326", "stat": "gir-200-plus", "heading": "GIR Percentage - 200+ yards", "first": "61.54", "tenth": "55.83", "twentyfifth": "51.82", "hundredth": "45.76", "last": "25.56", "top10avg": "58.59", "top25avg": "55.67", "top100avg": "50.04"},
{"yr": "2004", "statcode": "419", "statkey": "2004419", "stat": "going-for-green", "heading": "Going for the Green", "first": "76.12", "tenth": "67.54", "twentyfifth": "62.57", "hundredth": "50.00", "last": "19.48", "top10avg": "69.84", "top25avg": "66.30", "top100avg": "58.32"},
{"yr": "2004", "statcode": "111", "statkey": "2004111", "stat": "sand-saves", "heading": "Sand Save Percentage", "first": "62.32", "tenth": "58.88", "twentyfifth": "55.32", "hundredth": "48.95", "last": "31.82", "top10avg": "60.33", "top25avg": "57.96", "top100avg": "53.18"},
{"yr": "2004", "statcode": "364", "statkey": "2004364", "stat": "scrambling-from-fringe", "heading": "Scrambling from the Fringe", "first": "95.51", "tenth": "91.80", "twentyfifth": "89.66", "hundredth": "85.62", "last": "69.77", "top10avg": "93.38", "top25avg": "91.72", "top100avg": "88.64"},
{"yr": "2004", "statcode": "398", "statkey": "2004398", "stat": "1-putts-per-round", "heading": "1-Putts per Round", "first": "7.84", "tenth": "7.64", "twentyfifth": "7.47", "hundredth": "7.01", "last": "6.10", "top10avg": "7.72", "top25avg": "7.62", "top100avg": "7.31"},
{"yr": "2004", "statcode": "130", "statkey": "2004130", "stat": "scrambling", "heading": "Scrambling", "first": "66.13", "tenth": "63.60", "twentyfifth": "61.87", "hundredth": "58.41", "last": "42.78", "top10avg": "64.38", "top25avg": "63.31", "top100avg": "60.77"},
{"yr": "2004", "statcode": "119", "statkey": "2004119", "stat": "putts-per-round", "heading": "Putts Per Round", "first": "27.96", "tenth": "28.29", "twentyfifth": "28.50", "hundredth": "29.10", "last": "30.34", "top10avg": "28.14", "top25avg": "28.30", "top100avg": "28.69"},
{"yr": "2004", "statcode": "399", "statkey": "2004399", "stat": "2-putts-per-round", "heading": "2-Putts per Round", "first": "11.15", "tenth": "10.72", "twentyfifth": "10.60", "hundredth": "10.16", "last": "9.42", "top10avg": "10.86", "top25avg": "10.74", "top100avg": "10.45"},
{"yr": "2004", "statcode": "400", "statkey": "2004400", "stat": "3-putts-per-round", "heading": "3-Putts per Round", "first": ".94", "tenth": ".77", "twentyfifth": ".70", "hundredth": ".55", "last": ".25", "top10avg": "0.84", "top25avg": "0.78", "top100avg": "0.66"},
{"yr": "2004", "statcode": "484", "statkey": "2004484", "stat": "putting-inside-10", "heading": "Putting - Inside 10'", "first": "90.02", "tenth": "89.35", "twentyfifth": "88.64", "hundredth": "87.33", "last": "82.01", "top10avg": "89.63", "top25avg": "89.26", "top100avg": "88.29"},
{"yr": "2004", "statcode": "403", "statkey": "2004403", "stat": "putting-inside-5", "heading": "Putting from Inside 5'", "first": "98.51", "tenth": "97.84", "twentyfifth": "97.39", "hundredth": "96.47", "last": "93.55", "top10avg": "98.05", "top25avg": "97.76", "top100avg": "97.14"},
{"yr": "2005", "statcode": "102", "statkey": "2005102", "stat": "driving", "heading": "Driving Accuracy Percentage", "first": "75.97", "tenth": "71.43", "twentyfifth": "68.98", "hundredth": "62.81", "last": "45.36", "top10avg": "73.32", "top25avg": "71.45", "top100avg": "66.97"},
{"yr": "2005", "statcode": "103", "statkey": "2005103", "stat": "gir", "heading": "Greens in Regulation Percentage", "first": "71.81", "tenth": "69.49", "twentyfifth": "68.30", "hundredth": "65.05", "last": "55.49", "top10avg": "70.24", "top25avg": "69.38", "top100avg": "67.16"},
{"yr": "2005", "statcode": "329", "statkey": "2005329", "stat": "gir-125-150", "heading": "GIR Percentage - 125-150 yards", "first": "79.67", "tenth": "75.99", "twentyfifth": "74.30", "hundredth": "68.60", "last": "57.81", "top10avg": "77.45", "top25avg": "75.96", "top100avg": "72.31"},
{"yr": "2005", "statcode": "077", "statkey": "2005077", "stat": "gir-100-125", "heading": "GIR Percentage - 100-125 yards", "first": "83.72", "tenth": "80.65", "twentyfifth": "78.95", "hundredth": "74.38", "last": "62.07", "top10avg": "81.90", "top25avg": "80.57", "top100avg": "77.48"},
{"yr": "2005", "statcode": "02437", "statkey": "200502437", "stat": "GOFIR", "heading": "Greens or Fringe in Regulation", "first": "78.70", "tenth": "76.27", "twentyfifth": "75.18", "hundredth": "72.09", "last": "62.11", "top10avg": "76.89", "top25avg": "76.22", "top100avg": "74.25"},
{"yr": "2005", "statcode": "328", "statkey": "2005328", "stat": "gir-150-175", "heading": "GIR Percentage - 150-175 yards", "first": "71.92", "tenth": "68.85", "twentyfifth": "67.30", "hundredth": "61.65", "last": "47.68", "top10avg": "70.52", "top25avg": "68.98", "top100avg": "65.27"},
{"yr": "2005", "statcode": "326", "statkey": "2005326", "stat": "gir-200-plus", "heading": "GIR Percentage - 200+ yards", "first": "62.50", "tenth": "52.91", "twentyfifth": "50.81", "hundredth": "43.68", "last": "30.00", "top10avg": "55.44", "top25avg": "53.45", "top100avg": "48.35"},
{"yr": "2005", "statcode": "327", "statkey": "2005327", "stat": "gir-175-200", "heading": "GIR Percentage - 175-200 yards", "first": "67.69", "tenth": "60.95", "twentyfifth": "59.64", "hundredth": "53.94", "last": "37.58", "top10avg": "62.98", "top25avg": "61.29", "top100avg": "57.76"},
{"yr": "2005", "statcode": "130", "statkey": "2005130", "stat": "scrambling", "heading": "Scrambling", "first": "64.48", "tenth": "62.33", "twentyfifth": "61.47", "hundredth": "57.75", "last": "47.75", "top10avg": "63.11", "top25avg": "62.34", "top100avg": "60.02"},
{"yr": "2005", "statcode": "111", "statkey": "2005111", "stat": "sand-saves", "heading": "Sand Save Percentage", "first": "62.96", "tenth": "59.65", "twentyfifth": "55.90", "hundredth": "48.72", "last": "32.47", "top10avg": "60.88", "top25avg": "58.50", "top100avg": "53.79"},
{"yr": "2005", "statcode": "484", "statkey": "2005484", "stat": "putting-inside-10", "heading": "Putting - Inside 10'", "first": "90.02", "tenth": "89.06", "twentyfifth": "88.61", "hundredth": "87.22", "last": "83.51", "top10avg": "89.47", "top25avg": "89.06", "top100avg": "88.11"},
{"yr": "2005", "statcode": "364", "statkey": "2005364", "stat": "scrambling-from-fringe", "heading": "Scrambling from the Fringe", "first": "97.26", "tenth": "91.67", "twentyfifth": "89.81", "hundredth": "85.71", "last": "71.11", "top10avg": "94.33", "top25avg": "91.98", "top100avg": "88.48"},
{"yr": "2005", "statcode": "399", "statkey": "2005399", "stat": "2-putts-per-round", "heading": "2-Putts per Round", "first": "11.00", "tenth": "10.79", "twentyfifth": "10.62", "hundredth": "10.28", "last": "9.35", "top10avg": "10.89", "top25avg": "10.79", "top100avg": "10.54"},
{"yr": "2005", "statcode": "398", "statkey": "2005398", "stat": "1-putts-per-round", "heading": "1-Putts per Round", "first": "8.05", "tenth": "7.60", "twentyfifth": "7.41", "hundredth": "6.93", "last": "5.98", "top10avg": "7.74", "top25avg": "7.59", "top100avg": "7.25"},
{"yr": "2005", "statcode": "419", "statkey": "2005419", "stat": "going-for-green", "heading": "Going for the Green", "first": "73.02", "tenth": "64.52", "twentyfifth": "60.64", "hundredth": "48.74", "last": "17.54", "top10avg": "69.02", "top25avg": "64.90", "top100avg": "56.54"},
{"yr": "2005", "statcode": "119", "statkey": "2005119", "stat": "putts-per-round", "heading": "Putts Per Round", "first": "27.79", "tenth": "28.47", "twentyfifth": "28.62", "hundredth": "29.20", "last": "30.41", "top10avg": "28.20", "top25avg": "28.41", "top100avg": "28.80"},
{"yr": "2005", "statcode": "403", "statkey": "2005403", "stat": "putting-inside-5", "heading": "Putting from Inside 5'", "first": "98.14", "tenth": "97.68", "twentyfifth": "97.38", "hundredth": "96.52", "last": "92.67", "top10avg": "97.90", "top25avg": "97.66", "top100avg": "97.10"},
{"yr": "2005", "statcode": "400", "statkey": "2005400", "stat": "3-putts-per-round", "heading": "3-Putts per Round", "first": "1.04", "tenth": ".81", "twentyfifth": ".70", "hundredth": ".55", "last": ".29", "top10avg": "0.90", "top25avg": "0.80", "top100avg": "0.65"},
{"yr": "2006", "statcode": "102", "statkey": "2006102", "stat": "driving", "heading": "Driving Accuracy Percentage", "first": "78.43", "tenth": "72.90", "twentyfifth": "69.66", "hundredth": "63.10", "last": "49.75", "top10avg": "74.92", "top25avg": "72.52", "top100avg": "67.55"},
{"yr": "2006", "statcode": "103", "statkey": "2006103", "stat": "gir", "heading": "Greens in Regulation Percentage", "first": "74.15", "tenth": "69.32", "twentyfifth": "67.99", "hundredth": "65.33", "last": "56.87", "top10avg": "70.62", "top25avg": "69.38", "top100avg": "67.23"},
{"yr": "2006", "statcode": "02437", "statkey": "200602437", "stat": "GOFIR", "heading": "Greens or Fringe in Regulation", "first": "81.23", "tenth": "75.86", "twentyfifth": "74.69", "hundredth": "71.78", "last": "61.61", "top10avg": "77.31", "top25avg": "76.07", "top100avg": "73.86"},
{"yr": "2006", "statcode": "077", "statkey": "2006077", "stat": "gir-100-125", "heading": "GIR Percentage - 100-125 yards", "first": "85.53", "tenth": "81.31", "twentyfifth": "79.78", "hundredth": "74.32", "last": "62.64", "top10avg": "82.51", "top25avg": "81.33", "top100avg": "77.72"},
{"yr": "2006", "statcode": "329", "statkey": "2006329", "stat": "gir-125-150", "heading": "GIR Percentage - 125-150 yards", "first": "83.80", "tenth": "75.34", "twentyfifth": "73.52", "hundredth": "68.39", "last": "55.12", "top10avg": "77.59", "top25avg": "75.53", "top100avg": "71.95"},
{"yr": "2006", "statcode": "328", "statkey": "2006328", "stat": "gir-150-175", "heading": "GIR Percentage - 150-175 yards", "first": "74.44", "tenth": "68.33", "twentyfifth": "66.31", "hundredth": "61.68", "last": "47.06", "top10avg": "70.30", "top25avg": "68.32", "top100avg": "64.92"},
{"yr": "2006", "statcode": "327", "statkey": "2006327", "stat": "gir-175-200", "heading": "GIR Percentage - 175-200 yards", "first": "75.49", "tenth": "61.36", "twentyfifth": "59.73", "hundredth": "54.55", "last": "37.17", "top10avg": "63.90", "top25avg": "61.81", "top100avg": "57.74"},
{"yr": "2006", "statcode": "326", "statkey": "2006326", "stat": "gir-200-plus", "heading": "GIR Percentage - 200+ yards", "first": "61.54", "tenth": "56.05", "twentyfifth": "52.43", "hundredth": "46.15", "last": "31.01", "top10avg": "58.04", "top25avg": "55.59", "top100avg": "50.41"},
{"yr": "2006", "statcode": "111", "statkey": "2006111", "stat": "sand-saves", "heading": "Sand Save Percentage", "first": "63.64", "tenth": "58.90", "twentyfifth": "56.02", "hundredth": "48.60", "last": "33.91", "top10avg": "60.84", "top25avg": "58.58", "top100avg": "53.51"},
{"yr": "2006", "statcode": "419", "statkey": "2006419", "stat": "going-for-green", "heading": "Going for the Green", "first": "68.99", "tenth": "65.08", "twentyfifth": "61.35", "hundredth": "49.32", "last": "23.78", "top10avg": "67.31", "top25avg": "64.52", "top100avg": "57.08"},
{"yr": "2006", "statcode": "130", "statkey": "2006130", "stat": "scrambling", "heading": "Scrambling", "first": "66.45", "tenth": "62.81", "twentyfifth": "60.67", "hundredth": "57.62", "last": "49.02", "top10avg": "64.37", "top25avg": "62.50", "top100avg": "59.96"},
{"yr": "2006", "statcode": "119", "statkey": "2006119", "stat": "putts-per-round", "heading": "Putts Per Round", "first": "27.96", "tenth": "28.54", "twentyfifth": "28.71", "hundredth": "29.20", "last": "30.19", "top10avg": "28.33", "top25avg": "28.51", "top100avg": "28.86"},
{"yr": "2006", "statcode": "364", "statkey": "2006364", "stat": "scrambling-from-fringe", "heading": "Scrambling from the Fringe", "first": "97.30", "tenth": "93.94", "twentyfifth": "90.63", "hundredth": "86.30", "last": "72.45", "top10avg": "95.03", "top25avg": "93.02", "top100avg": "89.37"},
{"yr": "2006", "statcode": "398", "statkey": "2006398", "stat": "1-putts-per-round", "heading": "1-Putts per Round", "first": "7.77", "tenth": "7.48", "twentyfifth": "7.32", "hundredth": "6.96", "last": "6.08", "top10avg": "7.60", "top25avg": "7.48", "top100avg": "7.20"},
{"yr": "2006", "statcode": "484", "statkey": "2006484", "stat": "putting-inside-10", "heading": "Putting - Inside 10'", "first": "91.14", "tenth": "88.69", "twentyfifth": "88.21", "hundredth": "86.95", "last": "83.62", "top10avg": "89.35", "top25avg": "88.79", "top100avg": "87.85"},
{"yr": "2006", "statcode": "403", "statkey": "2006403", "stat": "putting-inside-5", "heading": "Putting from Inside 5'", "first": "98.07", "tenth": "97.49", "twentyfifth": "97.14", "hundredth": "96.27", "last": "92.86", "top10avg": "97.73", "top25avg": "97.44", "top100avg": "96.85"},
{"yr": "2007", "statcode": "02437", "statkey": "200702437", "stat": "GOFIR", "heading": "Greens or Fringe in Regulation", "first": "76.23", "tenth": "74.21", "twentyfifth": "72.78", "hundredth": "70.40", "last": "62.16", "top10avg": "74.96", "top25avg": "74.12", "top100avg": "72.11"},
{"yr": "2006", "statcode": "399", "statkey": "2006399", "stat": "2-putts-per-round", "heading": "2-Putts per Round", "first": "11.09", "tenth": "10.75", "twentyfifth": "10.64", "hundredth": "10.28", "last": "9.42", "top10avg": "10.91", "top25avg": "10.78", "top100avg": "10.52"},
{"yr": "2006", "statcode": "400", "statkey": "2006400", "stat": "3-putts-per-round", "heading": "3-Putts per Round", "first": "1.06", "tenth": ".81", "twentyfifth": ".70", "hundredth": ".55", "last": ".24", "top10avg": "0.90", "top25avg": "0.81", "top100avg": "0.67"},
{"yr": "2007", "statcode": "103", "statkey": "2007103", "stat": "gir", "heading": "Greens in Regulation Percentage", "first": "71.02", "tenth": "68.87", "twentyfifth": "67.02", "hundredth": "64.61", "last": "54.33", "top10avg": "69.74", "top25avg": "68.61", "top100avg": "66.40"},
{"yr": "2007", "statcode": "102", "statkey": "2007102", "stat": "driving", "heading": "Driving Accuracy Percentage", "first": "75.47", "tenth": "72.81", "twentyfifth": "70.05", "hundredth": "63.56", "last": "41.86", "top10avg": "73.83", "top25avg": "72.20", "top100avg": "67.52"},
{"yr": "2007", "statcode": "077", "statkey": "2007077", "stat": "gir-100-125", "heading": "GIR Percentage - 100-125 yards", "first": "85.06", "tenth": "80.19", "twentyfifth": "79.14", "hundredth": "74.48", "last": "62.60", "top10avg": "82.04", "top25avg": "80.51", "top100avg": "77.75"},
{"yr": "2007", "statcode": "328", "statkey": "2007328", "stat": "gir-150-175", "heading": "GIR Percentage - 150-175 yards", "first": "72.27", "tenth": "69.06", "twentyfifth": "66.49", "hundredth": "62.32", "last": "47.68", "top10avg": "70.15", "top25avg": "68.66", "top100avg": "65.20"},
{"yr": "2007", "statcode": "329", "statkey": "2007329", "stat": "gir-125-150", "heading": "GIR Percentage - 125-150 yards", "first": "80.68", "tenth": "76.17", "twentyfifth": "74.09", "hundredth": "70.19", "last": "54.49", "top10avg": "77.31", "top25avg": "75.90", "top100avg": "72.93"},
{"yr": "2007", "statcode": "364", "statkey": "2007364", "stat": "scrambling-from-fringe", "heading": "Scrambling from the Fringe", "first": "98.33", "tenth": "94.74", "twentyfifth": "92.86", "hundredth": "88.14", "last": "74.00", "top10avg": "95.73", "top25avg": "94.59", "top100avg": "91.20"},
{"yr": "2007", "statcode": "326", "statkey": "2007326", "stat": "gir-200-plus", "heading": "GIR Percentage - 200+ yards", "first": "62.03", "tenth": "54.92", "twentyfifth": "50.57", "hundredth": "45.66", "last": "29.41", "top10avg": "57.01", "top25avg": "54.41", "top100avg": "49.71"},
{"yr": "2007", "statcode": "327", "statkey": "2007327", "stat": "gir-175-200", "heading": "GIR Percentage - 175-200 yards", "first": "68.46", "tenth": "62.26", "twentyfifth": "59.21", "hundredth": "54.62", "last": "40.34", "top10avg": "63.83", "top25avg": "61.91", "top100avg": "57.98"},
{"yr": "2007", "statcode": "419", "statkey": "2007419", "stat": "going-for-green", "heading": "Going for the Green", "first": "69.76", "tenth": "65.05", "twentyfifth": "60.37", "hundredth": "49.58", "last": "22.53", "top10avg": "66.61", "top25avg": "64.38", "top100avg": "56.74"},
{"yr": "2007", "statcode": "111", "statkey": "2007111", "stat": "sand-saves", "heading": "Sand Save Percentage", "first": "68.10", "tenth": "58.39", "twentyfifth": "56.15", "hundredth": "49.02", "last": "34.45", "top10avg": "60.72", "top25avg": "58.48", "top100avg": "54.05"},
{"yr": "2007", "statcode": "130", "statkey": "2007130", "stat": "scrambling", "heading": "Scrambling", "first": "65.33", "tenth": "62.08", "twentyfifth": "60.60", "hundredth": "57.25", "last": "48.86", "top10avg": "63.23", "top25avg": "62.07", "top100avg": "59.67"},
{"yr": "2007", "statcode": "119", "statkey": "2007119", "stat": "putts-per-round", "heading": "Putts Per Round", "first": "27.88", "tenth": "28.40", "twentyfifth": "28.77", "hundredth": "29.32", "last": "30.64", "top10avg": "28.24", "top25avg": "28.47", "top100avg": "28.88"},
{"yr": "2008", "statcode": "102", "statkey": "2008102", "stat": "driving", "heading": "Driving Accuracy Percentage", "first": "80.42", "tenth": "72.47", "twentyfifth": "69.45", "hundredth": "62.94", "last": "49.01", "top10avg": "74.18", "top25avg": "72.35", "top100avg": "67.70"},
{"yr": "2007", "statcode": "403", "statkey": "2007403", "stat": "putting-inside-5", "heading": "Putting from Inside 5'", "first": "98.16", "tenth": "97.31", "twentyfifth": "97.03", "hundredth": "96.06", "last": "93.07", "top10avg": "97.62", "top25avg": "97.34", "top100avg": "96.72"},
{"yr": "2007", "statcode": "400", "statkey": "2007400", "stat": "3-putts-per-round", "heading": "3-Putts per Round", "first": ".87", "tenth": ".79", "twentyfifth": ".73", "hundredth": ".58", "last": ".29", "top10avg": "0.83", "top25avg": "0.79", "top100avg": "0.68"},
{"yr": "2007", "statcode": "484", "statkey": "2007484", "stat": "putting-inside-10", "heading": "Putting - Inside 10'", "first": "89.44", "tenth": "89.04", "twentyfifth": "88.36", "hundredth": "86.83", "last": "83.66", "top10avg": "89.21", "top25avg": "88.86", "top100avg": "87.80"},
{"yr": "2007", "statcode": "398", "statkey": "2007398", "stat": "1-putts-per-round", "heading": "1-Putts per Round", "first": "7.94", "tenth": "7.51", "twentyfifth": "7.21", "hundredth": "6.77", "last": "5.71", "top10avg": "7.69", "top25avg": "7.46", "top100avg": "7.11"},
{"yr": "2007", "statcode": "399", "statkey": "2007399", "stat": "2-putts-per-round", "heading": "2-Putts per Round", "first": "11.13", "tenth": "10.89", "twentyfifth": "10.54", "hundredth": "10.12", "last": "8.63", "top10avg": "10.97", "top25avg": "10.78", "top100avg": "10.41"},
{"yr": "2008", "statcode": "02437", "statkey": "200802437", "stat": "GOFIR", "heading": "Greens or Fringe in Regulation", "first": "76.68", "tenth": "74.62", "twentyfifth": "73.23", "hundredth": "70.42", "last": "62.66", "top10avg": "75.22", "top25avg": "74.32", "top100avg": "72.36"},
{"yr": "2008", "statcode": "103", "statkey": "2008103", "stat": "gir", "heading": "Greens in Regulation Percentage", "first": "71.10", "tenth": "69.08", "twentyfifth": "67.72", "hundredth": "64.90", "last": "57.84", "top10avg": "69.92", "top25avg": "68.87", "top100avg": "66.87"},
{"yr": "2008", "statcode": "419", "statkey": "2008419", "stat": "going-for-green", "heading": "Going for the Green", "first": "72.90", "tenth": "63.95", "twentyfifth": "59.17", "hundredth": "45.39", "last": "18.86", "top10avg": "66.74", "top25avg": "63.30", "top100avg": "54.68"},
{"yr": "2008", "statcode": "327", "statkey": "2008327", "stat": "gir-175-200", "heading": "GIR Percentage - 175-200 yards", "first": "64.84", "tenth": "62.56", "twentyfifth": "60.52", "hundredth": "55.40", "last": "43.36", "top10avg": "63.69", "top25avg": "62.16", "top100avg": "58.92"},
{"yr": "2008", "statcode": "077", "statkey": "2008077", "stat": "gir-100-125", "heading": "GIR Percentage - 100-125 yards", "first": "85.16", "tenth": "82.11", "twentyfifth": "80.54", "hundredth": "76.11", "last": "60.75", "top10avg": "83.25", "top25avg": "82.06", "top100avg": "79.20"},
{"yr": "2008", "statcode": "329", "statkey": "2008329", "stat": "gir-125-150", "heading": "GIR Percentage - 125-150 yards", "first": "81.78", "tenth": "77.26", "twentyfifth": "75.41", "hundredth": "71.50", "last": "59.23", "top10avg": "78.91", "top25avg": "77.20", "top100avg": "74.28"},
{"yr": "2008", "statcode": "328", "statkey": "2008328", "stat": "gir-150-175", "heading": "GIR Percentage - 150-175 yards", "first": "74.59", "tenth": "69.15", "twentyfifth": "67.60", "hundredth": "63.47", "last": "52.12", "top10avg": "70.45", "top25avg": "69.02", "top100avg": "66.12"},
{"yr": "2008", "statcode": "326", "statkey": "2008326", "stat": "gir-200-plus", "heading": "GIR Percentage - 200+ yards", "first": "58.88", "tenth": "55.13", "twentyfifth": "52.50", "hundredth": "45.04", "last": "34.58", "top10avg": "56.57", "top25avg": "54.62", "top100avg": "50.03"},
{"yr": "2008", "statcode": "130", "statkey": "2008130", "stat": "scrambling", "heading": "Scrambling", "first": "64.82", "tenth": "62.03", "twentyfifth": "60.43", "hundredth": "57.22", "last": "46.10", "top10avg": "63.06", "top25avg": "62.01", "top100avg": "59.46"},
{"yr": "2008", "statcode": "364", "statkey": "2008364", "stat": "scrambling-from-fringe", "heading": "Scrambling from the Fringe", "first": "98.41", "tenth": "94.20", "twentyfifth": "93.02", "hundredth": "87.50", "last": "72.41", "top10avg": "96.23", "top25avg": "94.63", "top100avg": "91.33"},
{"yr": "2008", "statcode": "399", "statkey": "2008399", "stat": "2-putts-per-round", "heading": "2-Putts per Round", "first": "11.32", "tenth": "10.74", "twentyfifth": "10.55", "hundredth": "9.98", "last": "8.29", "top10avg": "10.93", "top25avg": "10.76", "top100avg": "10.36"},
{"yr": "2008", "statcode": "398", "statkey": "2008398", "stat": "1-putts-per-round", "heading": "1-Putts per Round", "first": "7.84", "tenth": "7.44", "twentyfifth": "7.24", "hundredth": "6.64", "last": "5.32", "top10avg": "7.62", "top25avg": "7.43", "top100avg": "7.04"},
{"yr": "2008", "statcode": "111", "statkey": "2008111", "stat": "sand-saves", "heading": "Sand Save Percentage", "first": "63.71", "tenth": "58.06", "twentyfifth": "56.30", "hundredth": "50.00", "last": "36.80", "top10avg": "60.72", "top25avg": "58.52", "top100avg": "54.19"},
{"yr": "2008", "statcode": "119", "statkey": "2008119", "stat": "putts-per-round", "heading": "Putts Per Round", "first": "27.92", "tenth": "28.43", "twentyfifth": "28.72", "hundredth": "29.35", "last": "30.86", "top10avg": "28.22", "top25avg": "28.44", "top100avg": "28.90"},
{"yr": "2008", "statcode": "484", "statkey": "2008484", "stat": "putting-inside-10", "heading": "Putting - Inside 10'", "first": "89.44", "tenth": "88.61", "twentyfifth": "88.15", "hundredth": "86.79", "last": "82.42", "top10avg": "89.00", "top25avg": "88.59", "top100avg": "87.70"},
{"yr": "2008", "statcode": "400", "statkey": "2008400", "stat": "3-putts-per-round", "heading": "3-Putts per Round", "first": ".94", "tenth": ".81", "twentyfifth": ".70", "hundredth": ".57", "last": ".29", "top10avg": "0.85", "top25avg": "0.79", "top100avg": "0.66"},
{"yr": "2008", "statcode": "403", "statkey": "2008403", "stat": "putting-inside-5", "heading": "Putting from Inside 5'", "first": "97.96", "tenth": "97.30", "twentyfifth": "96.95", "hundredth": "96.21", "last": "92.09", "top10avg": "97.55", "top25avg": "97.28", "top100avg": "96.72"},
{"yr": "2009", "statcode": "102", "statkey": "2009102", "stat": "driving", "heading": "Driving Accuracy Percentage", "first": "74.09", "tenth": "71.47", "twentyfifth": "69.66", "hundredth": "63.73", "last": "48.02", "top10avg": "72.64", "top25avg": "71.32", "top100avg": "67.45"},
{"yr": "2009", "statcode": "111", "statkey": "2009111", "stat": "sand-saves", "heading": "Sand Save Percentage", "first": "64.43", "tenth": "58.93", "twentyfifth": "57.02", "hundredth": "49.67", "last": "31.67", "top10avg": "61.33", "top25avg": "59.20", "top100avg": "54.61"},
{"yr": "2009", "statcode": "103", "statkey": "2009103", "stat": "gir", "heading": "Greens in Regulation Percentage", "first": "70.89", "tenth": "68.95", "twentyfifth": "68.10", "hundredth": "65.51", "last": "52.35", "top10avg": "70.16", "top25avg": "69.11", "top100avg": "67.18"},
{"yr": "2009", "statcode": "02437", "statkey": "200902437", "stat": "GOFIR", "heading": "Greens or Fringe in Regulation", "first": "76.03", "tenth": "74.66", "twentyfifth": "73.53", "hundredth": "70.32", "last": "58.33", "top10avg": "75.23", "top25avg": "74.47", "top100avg": "72.40"},
{"yr": "2009", "statcode": "326", "statkey": "2009326", "stat": "gir-200-plus", "heading": "GIR Percentage - 200+ yards", "first": "57.55", "tenth": "53.69", "twentyfifth": "50.52", "hundredth": "43.90", "last": "29.02", "top10avg": "55.18", "top25avg": "53.15", "top100avg": "48.66"},
{"yr": "2009", "statcode": "077", "statkey": "2009077", "stat": "gir-100-125", "heading": "GIR Percentage - 100-125 yards", "first": "84.76", "tenth": "81.94", "twentyfifth": "79.56", "hundredth": "75.00", "last": "60.92", "top10avg": "82.84", "top25avg": "81.50", "top100avg": "78.20"},
{"yr": "2009", "statcode": "329", "statkey": "2009329", "stat": "gir-125-150", "heading": "GIR Percentage - 125-150 yards", "first": "79.45", "tenth": "76.44", "twentyfifth": "74.85", "hundredth": "70.64", "last": "60.00", "top10avg": "77.67", "top25avg": "76.39", "top100avg": "73.51"},
{"yr": "2009", "statcode": "328", "statkey": "2009328", "stat": "gir-150-175", "heading": "GIR Percentage - 150-175 yards", "first": "76.09", "tenth": "70.54", "twentyfifth": "68.94", "hundredth": "63.76", "last": "53.42", "top10avg": "72.08", "top25avg": "70.65", "top100avg": "67.16"},
{"yr": "2009", "statcode": "327", "statkey": "2009327", "stat": "gir-175-200", "heading": "GIR Percentage - 175-200 yards", "first": "67.04", "tenth": "62.67", "twentyfifth": "59.60", "hundredth": "55.04", "last": "39.44", "top10avg": "63.96", "top25avg": "62.03", "top100avg": "58.29"},
{"yr": "2009", "statcode": "130", "statkey": "2009130", "stat": "scrambling", "heading": "Scrambling", "first": "68.18", "tenth": "63.93", "twentyfifth": "62.60", "hundredth": "58.02", "last": "45.08", "top10avg": "65.23", "top25avg": "63.88", "top100avg": "61.02"},
{"yr": "2009", "statcode": "119", "statkey": "2009119", "stat": "putts-per-round", "heading": "Putts Per Round", "first": "28.00", "tenth": "28.29", "twentyfifth": "28.49", "hundredth": "29.19", "last": "30.86", "top10avg": "28.16", "top25avg": "28.31", "top100avg": "28.73"},
{"yr": "2009", "statcode": "364", "statkey": "2009364", "stat": "scrambling-from-fringe", "heading": "Scrambling from the Fringe", "first": "100.00", "tenth": "94.44", "twentyfifth": "92.86", "hundredth": "88.46", "last": "72.22", "top10avg": "96.08", "top25avg": "94.47", "top100avg": "91.40"},
{"yr": "2009", "statcode": "419", "statkey": "2009419", "stat": "going-for-green", "heading": "Going for the Green", "first": "71.82", "tenth": "66.08", "twentyfifth": "61.77", "hundredth": "47.92", "last": "22.34", "top10avg": "68.71", "top25avg": "65.72", "top100avg": "57.17"},
{"yr": "2009", "statcode": "398", "statkey": "2009398", "stat": "1-putts-per-round", "heading": "1-Putts per Round", "first": "7.91", "tenth": "7.65", "twentyfifth": "7.35", "hundredth": "6.75", "last": "5.20", "top10avg": "7.81", "top25avg": "7.61", "top100avg": "7.16"},
{"yr": "2009", "statcode": "484", "statkey": "2009484", "stat": "putting-inside-10", "heading": "Putting - Inside 10'", "first": "90.44", "tenth": "89.17", "twentyfifth": "88.40", "hundredth": "86.86", "last": "82.95", "top10avg": "89.45", "top25avg": "89.05", "top100avg": "87.85"},
{"yr": "2009", "statcode": "403", "statkey": "2009403", "stat": "putting-inside-5", "heading": "Putting from Inside 5'", "first": "98.18", "tenth": "97.61", "twentyfifth": "97.12", "hundredth": "96.15", "last": "92.18", "top10avg": "97.87", "top25avg": "97.53", "top100avg": "96.86"},
{"yr": "2009", "statcode": "399", "statkey": "2009399", "stat": "2-putts-per-round", "heading": "2-Putts per Round", "first": "11.00", "tenth": "10.71", "twentyfifth": "10.41", "hundredth": "9.77", "last": "8.20", "top10avg": "10.81", "top25avg": "10.66", "top100avg": "10.19"},
{"yr": "2009", "statcode": "400", "statkey": "2009400", "stat": "3-putts-per-round", "heading": "3-Putts per Round", "first": ".98", "tenth": ".80", "twentyfifth": ".69", "hundredth": ".51", "last": ".29", "top10avg": "0.84", "top25avg": "0.78", "top100avg": "0.63"},
{"yr": "2010", "statcode": "103", "statkey": "2010103", "stat": "gir", "heading": "Greens in Regulation Percentage", "first": "72.49", "tenth": "70.49", "twentyfifth": "69.78", "hundredth": "66.75", "last": "57.89", "top10avg": "71.46", "top25avg": "70.63", "top100avg": "68.87"},
{"yr": "2010", "statcode": "329", "statkey": "2010329", "stat": "gir-125-150", "heading": "GIR Percentage - 125-150 yards", "first": "80.41", "tenth": "78.53", "twentyfifth": "75.91", "hundredth": "72.09", "last": "58.88", "top10avg": "79.53", "top25avg": "77.92", "top100avg": "74.73"},
{"yr": "2010", "statcode": "02437", "statkey": "201002437", "stat": "GOFIR", "heading": "Greens or Fringe in Regulation", "first": "77.52", "tenth": "75.29", "twentyfifth": "74.32", "hundredth": "71.81", "last": "62.50", "top10avg": "76.04", "top25avg": "75.24", "top100avg": "73.56"},
{"yr": "2010", "statcode": "077", "statkey": "2010077", "stat": "gir-100-125", "heading": "GIR Percentage - 100-125 yards", "first": "86.96", "tenth": "84.21", "twentyfifth": "81.51", "hundredth": "76.80", "last": "63.11", "top10avg": "85.34", "top25avg": "83.61", "top100avg": "80.02"},
{"yr": "2010", "statcode": "102", "statkey": "2010102", "stat": "driving", "heading": "Driving Accuracy Percentage", "first": "76.08", "tenth": "71.01", "twentyfifth": "69.01", "hundredth": "63.40", "last": "50.15", "top10avg": "73.03", "top25avg": "71.22", "top100avg": "67.24"},
{"yr": "2010", "statcode": "328", "statkey": "2010328", "stat": "gir-150-175", "heading": "GIR Percentage - 150-175 yards", "first": "76.09", "tenth": "71.30", "twentyfifth": "69.61", "hundredth": "65.40", "last": "50.00", "top10avg": "72.98", "top25avg": "71.44", "top100avg": "68.34"},
{"yr": "2010", "statcode": "326", "statkey": "2010326", "stat": "gir-200-plus", "heading": "GIR Percentage - 200+ yards", "first": "60.94", "tenth": "56.69", "twentyfifth": "53.52", "hundredth": "48.70", "last": "31.69", "top10avg": "58.99", "top25avg": "56.51", "top100avg": "52.32"},
{"yr": "2010", "statcode": "419", "statkey": "2010419", "stat": "going-for-green", "heading": "Going for the Green", "first": "71.85", "tenth": "65.33", "twentyfifth": "59.17", "hundredth": "47.40", "last": "21.02", "top10avg": "67.15", "top25avg": "63.91", "top100avg": "55.93"},
{"yr": "2010", "statcode": "130", "statkey": "2010130", "stat": "scrambling", "heading": "Scrambling", "first": "67.16", "tenth": "64.32", "twentyfifth": "62.33", "hundredth": "57.91", "last": "47.49", "top10avg": "65.14", "top25avg": "63.94", "top100avg": "60.88"},
{"yr": "2010", "statcode": "327", "statkey": "2010327", "stat": "gir-175-200", "heading": "GIR Percentage - 175-200 yards", "first": "66.10", "tenth": "63.52", "twentyfifth": "61.26", "hundredth": "56.54", "last": "43.98", "top10avg": "64.42", "top25avg": "63.11", "top100avg": "59.76"},
{"yr": "2010", "statcode": "364", "statkey": "2010364", "stat": "scrambling-from-fringe", "heading": "Scrambling from the Fringe", "first": "98.04", "tenth": "95.45", "twentyfifth": "93.33", "hundredth": "88.24", "last": "74.65", "top10avg": "96.46", "top25avg": "94.88", "top100avg": "91.86"},
{"yr": "2010", "statcode": "111", "statkey": "2010111", "stat": "sand-saves", "heading": "Sand Save Percentage", "first": "66.39", "tenth": "59.18", "twentyfifth": "56.25", "hundredth": "49.32", "last": "33.78", "top10avg": "61.10", "top25avg": "59.08", "top100avg": "54.01"},
{"yr": "2010", "statcode": "119", "statkey": "2010119", "stat": "putts-per-round", "heading": "Putts Per Round", "first": "27.97", "tenth": "28.53", "twentyfifth": "28.75", "hundredth": "29.41", "last": "31.00", "top10avg": "28.28", "top25avg": "28.52", "top100avg": "28.95"},
{"yr": "2010", "statcode": "398", "statkey": "2010398", "stat": "1-putts-per-round", "heading": "1-Putts per Round", "first": "7.91", "tenth": "7.39", "twentyfifth": "7.22", "hundredth": "6.58", "last": "5.11", "top10avg": "7.61", "top25avg": "7.41", "top100avg": "7.00"},
{"yr": "2010", "statcode": "399", "statkey": "2010399", "stat": "2-putts-per-round", "heading": "2-Putts per Round", "first": "11.43", "tenth": "10.77", "twentyfifth": "10.55", "hundredth": "10.04", "last": "8.57", "top10avg": "11.00", "top25avg": "10.78", "top100avg": "10.39"},
{"yr": "2011", "statcode": "103", "statkey": "2011103", "stat": "gir", "heading": "Greens in Regulation Percentage", "first": "71.68", "tenth": "69.48", "twentyfifth": "68.63", "hundredth": "65.42", "last": "59.49", "top10avg": "70.56", "top25avg": "69.63", "top100avg": "67.39"},
{"yr": "2010", "statcode": "403", "statkey": "2010403", "stat": "putting-inside-5", "heading": "Putting from Inside 5'", "first": "98.68", "tenth": "97.74", "twentyfifth": "97.38", "hundredth": "96.34", "last": "92.68", "top10avg": "98.06", "top25avg": "97.77", "top100avg": "97.00"},
{"yr": "2010", "statcode": "400", "statkey": "2010400", "stat": "3-putts-per-round", "heading": "3-Putts per Round", "first": ".85", "tenth": ".76", "twentyfifth": ".67", "hundredth": ".54", "last": ".25", "top10avg": "0.79", "top25avg": "0.75", "top100avg": "0.64"},
{"yr": "2010", "statcode": "484", "statkey": "2010484", "stat": "putting-inside-10", "heading": "Putting - Inside 10'", "first": "90.67", "tenth": "89.24", "twentyfifth": "88.52", "hundredth": "87.13", "last": "83.05", "top10avg": "89.73", "top25avg": "89.21", "top100avg": "88.12"},
{"yr": "2011", "statcode": "102", "statkey": "2011102", "stat": "driving", "heading": "Driving Accuracy Percentage", "first": "75.65", "tenth": "70.33", "twentyfifth": "67.31", "hundredth": "61.43", "last": "46.99", "top10avg": "72.38", "top25avg": "70.03", "top100avg": "65.61"},
{"yr": "2011", "statcode": "02437", "statkey": "201102437", "stat": "GOFIR", "heading": "Greens or Fringe in Regulation", "first": "76.31", "tenth": "74.67", "twentyfifth": "73.61", "hundredth": "70.40", "last": "63.41", "top10avg": "75.33", "top25avg": "74.51", "top100avg": "72.56"},
{"yr": "2011", "statcode": "077", "statkey": "2011077", "stat": "gir-100-125", "heading": "GIR Percentage - 100-125 yards", "first": "86.14", "tenth": "81.67", "twentyfifth": "80.16", "hundredth": "74.84", "last": "64.85", "top10avg": "83.65", "top25avg": "81.91", "top100avg": "78.49"},
{"yr": "2011", "statcode": "329", "statkey": "2011329", "stat": "gir-125-150", "heading": "GIR Percentage - 125-150 yards", "first": "81.27", "tenth": "77.78", "twentyfifth": "74.86", "hundredth": "70.67", "last": "60.48", "top10avg": "78.94", "top25avg": "77.18", "top100avg": "73.86"},
{"yr": "2011", "statcode": "328", "statkey": "2011328", "stat": "gir-150-175", "heading": "GIR Percentage - 150-175 yards", "first": "73.84", "tenth": "70.27", "twentyfifth": "68.41", "hundredth": "63.25", "last": "53.74", "top10avg": "71.44", "top25avg": "70.12", "top100avg": "66.84"},
{"yr": "2011", "statcode": "327", "statkey": "2011327", "stat": "gir-175-200", "heading": "GIR Percentage - 175-200 yards", "first": "67.68", "tenth": "61.79", "twentyfifth": "60.31", "hundredth": "54.59", "last": "40.48", "top10avg": "63.46", "top25avg": "62.02", "top100avg": "58.34"},
{"yr": "2011", "statcode": "111", "statkey": "2011111", "stat": "sand-saves", "heading": "Sand Save Percentage", "first": "63.40", "tenth": "58.11", "twentyfifth": "55.17", "hundredth": "47.92", "last": "30.49", "top10avg": "59.84", "top25avg": "57.56", "top100avg": "52.90"},
{"yr": "2011", "statcode": "326", "statkey": "2011326", "stat": "gir-200-plus", "heading": "GIR Percentage - 200+ yards", "first": "58.33", "tenth": "55.43", "twentyfifth": "51.56", "hundredth": "45.16", "last": "30.87", "top10avg": "56.83", "top25avg": "54.64", "top100avg": "49.83"},
{"yr": "2011", "statcode": "419", "statkey": "2011419", "stat": "going-for-green", "heading": "Going for the Green", "first": "74.04", "tenth": "68.30", "twentyfifth": "63.71", "hundredth": "50.00", "last": "22.35", "top10avg": "70.58", "top25avg": "67.62", "top100avg": "58.48"},
{"yr": "2011", "statcode": "130", "statkey": "2011130", "stat": "scrambling", "heading": "Scrambling", "first": "65.17", "tenth": "63.10", "twentyfifth": "61.21", "hundredth": "57.58", "last": "47.91", "top10avg": "64.06", "top25avg": "62.83", "top100avg": "60.08"},
{"yr": "2011", "statcode": "119", "statkey": "2011119", "stat": "putts-per-round", "heading": "Putts Per Round", "first": "27.75", "tenth": "28.39", "twentyfifth": "28.66", "hundredth": "29.26", "last": "30.84", "top10avg": "28.15", "top25avg": "28.38", "top100avg": "28.85"},
{"yr": "2011", "statcode": "364", "statkey": "2011364", "stat": "scrambling-from-fringe", "heading": "Scrambling from the Fringe", "first": "100.00", "tenth": "95.38", "twentyfifth": "92.98", "hundredth": "88.24", "last": "76.00", "top10avg": "97.33", "top25avg": "95.25", "top100avg": "91.67"},
{"yr": "2012", "statcode": "102", "statkey": "2012102", "stat": "driving", "heading": "Driving Accuracy Percentage", "first": "73.00", "tenth": "68.72", "twentyfifth": "65.91", "hundredth": "61.12", "last": "47.27", "top10avg": "70.35", "top25avg": "68.58", "top100avg": "64.60"},
{"yr": "2012", "statcode": "103", "statkey": "2012103", "stat": "gir", "heading": "Greens in Regulation Percentage", "first": "70.34", "tenth": "69.13", "twentyfifth": "67.80", "hundredth": "64.96", "last": "57.74", "top10avg": "69.52", "top25avg": "68.89", "top100avg": "66.95"},
{"yr": "2011", "statcode": "484", "statkey": "2011484", "stat": "putting-inside-10", "heading": "Putting - Inside 10'", "first": "90.50", "tenth": "89.16", "twentyfifth": "88.67", "hundredth": "87.13", "last": "84.10", "top10avg": "89.74", "top25avg": "89.22", "top100avg": "88.20"},
{"yr": "2011", "statcode": "399", "statkey": "2011399", "stat": "2-putts-per-round", "heading": "2-Putts per Round", "first": "11.35", "tenth": "10.65", "twentyfifth": "10.45", "hundredth": "9.88", "last": "8.75", "top10avg": "10.90", "top25avg": "10.68", "top100avg": "10.30"},
{"yr": "2011", "statcode": "398", "statkey": "2011398", "stat": "1-putts-per-round", "heading": "1-Putts per Round", "first": "8.06", "tenth": "7.51", "twentyfifth": "7.27", "hundredth": "6.64", "last": "5.14", "top10avg": "7.75", "top25avg": "7.52", "top100avg": "7.06"},
{"yr": "2011", "statcode": "400", "statkey": "2011400", "stat": "3-putts-per-round", "heading": "3-Putts per Round", "first": "1.00", "tenth": ".73", "twentyfifth": ".68", "hundredth": ".53", "last": ".22", "top10avg": "0.82", "top25avg": "0.75", "top100avg": "0.63"},
{"yr": "2012", "statcode": "077", "statkey": "2012077", "stat": "gir-100-125", "heading": "GIR Percentage - 100-125 yards", "first": "86.59", "tenth": "82.41", "twentyfifth": "80.58", "hundredth": "76.19", "last": "62.50", "top10avg": "84.27", "top25avg": "82.51", "top100avg": "79.50"},
{"yr": "2012", "statcode": "327", "statkey": "2012327", "stat": "gir-175-200", "heading": "GIR Percentage - 175-200 yards", "first": "65.13", "tenth": "61.64", "twentyfifth": "60.28", "hundredth": "54.38", "last": "43.41", "top10avg": "63.08", "top25avg": "61.74", "top100avg": "57.90"},
{"yr": "2012", "statcode": "02437", "statkey": "201202437", "stat": "GOFIR", "heading": "Greens or Fringe in Regulation", "first": "75.00", "tenth": "74.07", "twentyfifth": "73.39", "hundredth": "70.12", "last": "61.38", "top10avg": "74.36", "top25avg": "73.97", "top100avg": "72.09"},
{"yr": "2011", "statcode": "403", "statkey": "2011403", "stat": "putting-inside-5", "heading": "Putting from Inside 5'", "first": "98.32", "tenth": "97.62", "twentyfifth": "97.35", "hundredth": "96.28", "last": "93.76", "top10avg": "97.83", "top25avg": "97.59", "top100avg": "96.95"},
{"yr": "2012", "statcode": "328", "statkey": "2012328", "stat": "gir-150-175", "heading": "GIR Percentage - 150-175 yards", "first": "72.57", "tenth": "69.49", "twentyfifth": "67.95", "hundredth": "64.04", "last": "49.77", "top10avg": "70.39", "top25avg": "69.31", "top100avg": "66.69"},
{"yr": "2012", "statcode": "326", "statkey": "2012326", "stat": "gir-200-plus", "heading": "GIR Percentage - 200+ yards", "first": "62.50", "tenth": "53.85", "twentyfifth": "51.00", "hundredth": "44.70", "last": "31.78", "top10avg": "56.75", "top25avg": "54.11", "top100avg": "49.28"},
{"yr": "2012", "statcode": "329", "statkey": "2012329", "stat": "gir-125-150", "heading": "GIR Percentage - 125-150 yards", "first": "82.52", "tenth": "78.74", "twentyfifth": "75.66", "hundredth": "70.92", "last": "57.69", "top10avg": "80.55", "top25avg": "78.26", "top100avg": "74.25"},
{"yr": "2012", "statcode": "364", "statkey": "2012364", "stat": "scrambling-from-fringe", "heading": "Scrambling from the Fringe", "first": "100.00", "tenth": "95.12", "twentyfifth": "93.10", "hundredth": "87.72", "last": "74.07", "top10avg": "96.49", "top25avg": "95.13", "top100avg": "91.61"},
{"yr": "2012", "statcode": "419", "statkey": "2012419", "stat": "going-for-green", "heading": "Going for the Green", "first": "80.61", "tenth": "69.35", "twentyfifth": "63.31", "hundredth": "51.83", "last": "27.00", "top10avg": "72.45", "top25avg": "67.97", "top100avg": "59.97"},
{"yr": "2012", "statcode": "130", "statkey": "2012130", "stat": "scrambling", "heading": "Scrambling", "first": "64.38", "tenth": "62.08", "twentyfifth": "60.98", "hundredth": "56.96", "last": "48.30", "top10avg": "63.04", "top25avg": "62.11", "top100avg": "59.51"},
{"yr": "2012", "statcode": "111", "statkey": "2012111", "stat": "sand-saves", "heading": "Sand Save Percentage", "first": "65.44", "tenth": "59.41", "twentyfifth": "55.30", "hundredth": "47.57", "last": "29.73", "top10avg": "62.16", "top25avg": "59.08", "top100avg": "53.22"},
{"yr": "2012", "statcode": "484", "statkey": "2012484", "stat": "putting-inside-10", "heading": "Putting - Inside 10'", "first": "90.27", "tenth": "89.02", "twentyfifth": "88.58", "hundredth": "86.97", "last": "83.33", "top10avg": "89.46", "top25avg": "89.02", "top100avg": "88.08"},
{"yr": "2012", "statcode": "119", "statkey": "2012119", "stat": "putts-per-round", "heading": "Putts Per Round", "first": "27.89", "tenth": "28.42", "twentyfifth": "28.65", "hundredth": "29.28", "last": "30.50", "top10avg": "28.18", "top25avg": "28.41", "top100avg": "28.83"},
{"yr": "2013", "statcode": "102", "statkey": "2013102", "stat": "driving", "heading": "Driving Accuracy Percentage", "first": "71.81", "tenth": "69.28", "twentyfifth": "66.61", "hundredth": "60.70", "last": "45.58", "top10avg": "70.29", "top25avg": "68.86", "top100avg": "64.64"},
{"yr": "2013", "statcode": "103", "statkey": "2013103", "stat": "gir", "heading": "Greens in Regulation Percentage", "first": "71.96", "tenth": "68.84", "twentyfifth": "67.58", "hundredth": "64.81", "last": "56.68", "top10avg": "69.87", "top25avg": "68.76", "top100avg": "66.78"},
{"yr": "2012", "statcode": "398", "statkey": "2012398", "stat": "1-putts-per-round", "heading": "1-Putts per Round", "first": "7.97", "tenth": "7.54", "twentyfifth": "7.35", "hundredth": "6.79", "last": "5.54", "top10avg": "7.74", "top25avg": "7.55", "top100avg": "7.17"},
{"yr": "2012", "statcode": "399", "statkey": "2012399", "stat": "2-putts-per-round", "heading": "2-Putts per Round", "first": "11.09", "tenth": "10.72", "twentyfifth": "10.56", "hundredth": "10.07", "last": "9.02", "top10avg": "10.84", "top25avg": "10.72", "top100avg": "10.38"},
{"yr": "2012", "statcode": "400", "statkey": "2012400", "stat": "3-putts-per-round", "heading": "3-Putts per Round", "first": ".90", "tenth": ".77", "twentyfifth": ".68", "hundredth": ".54", "last": ".26", "top10avg": "0.83", "top25avg": "0.76", "top100avg": "0.64"},
{"yr": "2013", "statcode": "077", "statkey": "2013077", "stat": "gir-100-125", "heading": "GIR Percentage - 100-125 yards", "first": "85.42", "tenth": "82.42", "twentyfifth": "80.28", "hundredth": "74.56", "last": "64.65", "top10avg": "83.72", "top25avg": "82.36", "top100avg": "78.47"},
{"yr": "2012", "statcode": "403", "statkey": "2012403", "stat": "putting-inside-5", "heading": "Putting from Inside 5'", "first": "98.51", "tenth": "97.76", "twentyfifth": "97.23", "hundredth": "96.38", "last": "93.56", "top10avg": "98.10", "top25avg": "97.71", "top100avg": "96.98"},
{"yr": "2013", "statcode": "328", "statkey": "2013328", "stat": "gir-150-175", "heading": "GIR Percentage - 150-175 yards", "first": "72.81", "tenth": "69.75", "twentyfifth": "68.31", "hundredth": "63.04", "last": "52.29", "top10avg": "71.00", "top25avg": "69.83", "top100avg": "66.65"},
{"yr": "2013", "statcode": "02437", "statkey": "201302437", "stat": "GOFIR", "heading": "Greens or Fringe in Regulation", "first": "77.02", "tenth": "74.00", "twentyfifth": "72.55", "hundredth": "69.41", "last": "61.21", "top10avg": "75.02", "top25avg": "73.85", "top100avg": "71.56"},
{"yr": "2013", "statcode": "111", "statkey": "2013111", "stat": "sand-saves", "heading": "Sand Save Percentage", "first": "67.18", "tenth": "61.47", "twentyfifth": "58.70", "hundredth": "50.00", "last": "29.51", "top10avg": "63.46", "top25avg": "61.29", "top100avg": "55.34"},
{"yr": "2013", "statcode": "329", "statkey": "2013329", "stat": "gir-125-150", "heading": "GIR Percentage - 125-150 yards", "first": "80.23", "tenth": "77.44", "twentyfifth": "75.38", "hundredth": "70.69", "last": "56.84", "top10avg": "78.34", "top25avg": "77.06", "top100avg": "73.75"},
{"yr": "2013", "statcode": "327", "statkey": "2013327", "stat": "gir-175-200", "heading": "GIR Percentage - 175-200 yards", "first": "65.52", "tenth": "61.13", "twentyfifth": "59.47", "hundredth": "53.71", "last": "41.23", "top10avg": "62.94", "top25avg": "61.35", "top100avg": "57.64"},
{"yr": "2013", "statcode": "326", "statkey": "2013326", "stat": "gir-200-plus", "heading": "GIR Percentage - 200+ yards", "first": "62.18", "tenth": "54.62", "twentyfifth": "51.00", "hundredth": "43.94", "last": "29.46", "top10avg": "56.75", "top25avg": "54.29", "top100avg": "48.74"},
{"yr": "2013", "statcode": "419", "statkey": "2013419", "stat": "going-for-green", "heading": "Going for the Green", "first": "76.06", "tenth": "63.95", "twentyfifth": "59.89", "hundredth": "47.78", "last": "25.44", "top10avg": "68.62", "top25avg": "64.79", "top100avg": "56.60"},
{"yr": "2013", "statcode": "130", "statkey": "2013130", "stat": "scrambling", "heading": "Scrambling", "first": "66.19", "tenth": "63.80", "twentyfifth": "61.49", "hundredth": "57.39", "last": "48.74", "top10avg": "64.76", "top25avg": "63.27", "top100avg": "60.29"},
{"yr": "2013", "statcode": "364", "statkey": "2013364", "stat": "scrambling-from-fringe", "heading": "Scrambling from the Fringe", "first": "100.00", "tenth": "95.83", "twentyfifth": "93.75", "hundredth": "87.50", "last": "68.42", "top10avg": "97.28", "top25avg": "95.57", "top100avg": "91.93"},
{"yr": "2013", "statcode": "119", "statkey": "2013119", "stat": "putts-per-round", "heading": "Putts Per Round", "first": "27.51", "tenth": "28.38", "twentyfifth": "28.63", "hundredth": "29.24", "last": "30.89", "top10avg": "28.13", "top25avg": "28.36", "top100avg": "28.80"},
{"yr": "2013", "statcode": "398", "statkey": "2013398", "stat": "1-putts-per-round", "heading": "1-Putts per Round", "first": "8.23", "tenth": "7.62", "twentyfifth": "7.46", "hundredth": "6.95", "last": "5.64", "top10avg": "7.83", "top25avg": "7.65", "top100avg": "7.29"},
{"yr": "2014", "statcode": "102", "statkey": "2014102", "stat": "driving", "heading": "Driving Accuracy Percentage", "first": "75.49", "tenth": "69.57", "twentyfifth": "66.87", "hundredth": "60.66", "last": "50.00", "top10avg": "71.92", "top25avg": "69.51", "top100avg": "64.81"},
{"yr": "2013", "statcode": "399", "statkey": "2013399", "stat": "2-putts-per-round", "heading": "2-Putts per Round", "first": "11.23", "tenth": "10.84", "twentyfifth": "10.66", "hundredth": "10.16", "last": "9.09", "top10avg": "11.00", "top25avg": "10.84", "top100avg": "10.51"},
{"yr": "2013", "statcode": "400", "statkey": "2013400", "stat": "3-putts-per-round", "heading": "3-Putts per Round", "first": "1.00", "tenth": ".80", "twentyfifth": ".71", "hundredth": ".55", "last": ".33", "top10avg": "0.89", "top25avg": "0.80", "top100avg": "0.66"},
{"yr": "2013", "statcode": "484", "statkey": "2013484", "stat": "putting-inside-10", "heading": "Putting - Inside 10'", "first": "89.97", "tenth": "88.95", "twentyfifth": "88.27", "hundredth": "86.73", "last": "83.38", "top10avg": "89.29", "top25avg": "88.85", "top100avg": "87.79"},
{"yr": "2013", "statcode": "403", "statkey": "2013403", "stat": "putting-inside-5", "heading": "Putting from Inside 5'", "first": "98.52", "tenth": "97.55", "twentyfifth": "97.29", "hundredth": "96.31", "last": "93.25", "top10avg": "97.82", "top25avg": "97.57", "top100avg": "96.96"},
{"yr": "2014", "statcode": "103", "statkey": "2014103", "stat": "gir", "heading": "Greens in Regulation Percentage", "first": "72.43", "tenth": "68.79", "twentyfifth": "67.85", "hundredth": "64.51", "last": "57.44", "top10avg": "69.99", "top25avg": "68.98", "top100avg": "66.76"},
{"yr": "2014", "statcode": "077", "statkey": "2014077", "stat": "gir-100-125", "heading": "GIR Percentage - 100-125 yards", "first": "86.67", "tenth": "83.19", "twentyfifth": "81.89", "hundredth": "74.83", "last": "63.48", "top10avg": "84.09", "top25avg": "83.08", "top100avg": "79.28"},
{"yr": "2014", "statcode": "02437", "statkey": "201402437", "stat": "GOFIR", "heading": "Greens or Fringe in Regulation", "first": "76.09", "tenth": "73.61", "twentyfifth": "72.48", "hundredth": "69.05", "last": "61.53", "top10avg": "74.34", "top25avg": "73.45", "top100avg": "71.24"},
{"yr": "2014", "statcode": "328", "statkey": "2014328", "stat": "gir-150-175", "heading": "GIR Percentage - 150-175 yards", "first": "74.51", "tenth": "70.77", "twentyfifth": "69.23", "hundredth": "64.09", "last": "55.62", "top10avg": "72.19", "top25avg": "70.78", "top100avg": "67.52"},
{"yr": "2014", "statcode": "327", "statkey": "2014327", "stat": "gir-175-200", "heading": "GIR Percentage - 175-200 yards", "first": "70.25", "tenth": "62.07", "twentyfifth": "59.26", "hundredth": "53.58", "last": "39.09", "top10avg": "64.49", "top25avg": "62.12", "top100avg": "57.75"},
{"yr": "2014", "statcode": "329", "statkey": "2014329", "stat": "gir-125-150", "heading": "GIR Percentage - 125-150 yards", "first": "81.65", "tenth": "76.71", "twentyfifth": "74.91", "hundredth": "70.83", "last": "56.98", "top10avg": "78.10", "top25avg": "76.72", "top100avg": "73.71"},
{"yr": "2014", "statcode": "326", "statkey": "2014326", "stat": "gir-200-plus", "heading": "GIR Percentage - 200+ yards", "first": "60.76", "tenth": "53.27", "twentyfifth": "50.00", "hundredth": "42.79", "last": "30.10", "top10avg": "55.88", "top25avg": "53.10", "top100avg": "47.70"},
{"yr": "2014", "statcode": "419", "statkey": "2014419", "stat": "going-for-green", "heading": "Going for the Green", "first": "76.14", "tenth": "65.49", "twentyfifth": "61.30", "hundredth": "49.41", "last": "18.75", "top10avg": "68.26", "top25avg": "65.02", "top100avg": "56.80"},
{"yr": "2014", "statcode": "111", "statkey": "2014111", "stat": "sand-saves", "heading": "Sand Save Percentage", "first": "62.15", "tenth": "59.18", "twentyfifth": "56.52", "hundredth": "49.24", "last": "34.07", "top10avg": "60.81", "top25avg": "59.03", "top100avg": "54.17"},
{"yr": "2014", "statcode": "364", "statkey": "2014364", "stat": "scrambling-from-fringe", "heading": "Scrambling from the Fringe", "first": "97.70", "tenth": "96.10", "twentyfifth": "93.33", "hundredth": "88.64", "last": "74.58", "top10avg": "96.91", "top25avg": "95.62", "top100avg": "92.07"},
{"yr": "2014", "statcode": "130", "statkey": "2014130", "stat": "scrambling", "heading": "Scrambling", "first": "69.33", "tenth": "63.19", "twentyfifth": "61.55", "hundredth": "57.79", "last": "47.98", "top10avg": "64.98", "top25avg": "63.18", "top100avg": "60.51"},
{"yr": "2014", "statcode": "400", "statkey": "2014400", "stat": "3-putts-per-round", "heading": "3-Putts per Round", "first": ".96", "tenth": ".73", "twentyfifth": ".65", "hundredth": ".50", "last": ".29", "top10avg": "0.80", "top25avg": "0.73", "top100avg": "0.60"},
{"yr": "2014", "statcode": "119", "statkey": "2014119", "stat": "putts-per-round", "heading": "Putts Per Round", "first": "27.77", "tenth": "28.37", "twentyfifth": "28.57", "hundredth": "29.11", "last": "30.85", "top10avg": "28.18", "top25avg": "28.36", "top100avg": "28.74"},
{"yr": "2014", "statcode": "398", "statkey": "2014398", "stat": "1-putts-per-round", "heading": "1-Putts per Round", "first": "8.26", "tenth": "7.68", "twentyfifth": "7.48", "hundredth": "7.01", "last": "5.78", "top10avg": "7.84", "top25avg": "7.66", "top100avg": "7.32"},
{"yr": "2014", "statcode": "399", "statkey": "2014399", "stat": "2-putts-per-round", "heading": "2-Putts per Round", "first": "11.37", "tenth": "10.93", "twentyfifth": "10.66", "hundredth": "10.20", "last": "9.08", "top10avg": "11.12", "top25avg": "10.91", "top100avg": "10.53"},
{"yr": "2014", "statcode": "484", "statkey": "2014484", "stat": "putting-inside-10", "heading": "Putting - Inside 10'", "first": "90.57", "tenth": "89.14", "twentyfifth": "88.60", "hundredth": "87.14", "last": "81.22", "top10avg": "89.52", "top25avg": "89.09", "top100avg": "88.12"},
{"yr": "2014", "statcode": "403", "statkey": "2014403", "stat": "putting-inside-5", "heading": "Putting from Inside 5'", "first": "98.92", "tenth": "97.80", "twentyfifth": "97.39", "hundredth": "96.47", "last": "91.17", "top10avg": "98.03", "top25avg": "97.76", "top100avg": "97.10"},
{"yr": "2015", "statcode": "329", "statkey": "2015329", "stat": "gir-125-150", "heading": "GIR Percentage - 125-150 yards", "first": "83.19", "tenth": "78.57", "twentyfifth": "75.74", "hundredth": "70.15", "last": "60.64", "top10avg": "80.38", "top25avg": "78.21", "top100avg": "73.93"},
{"yr": "2015", "statcode": "02437", "statkey": "201502437", "stat": "GOFIR", "heading": "Greens or Fringe in Regulation", "first": "77.51", "tenth": "74.46", "twentyfifth": "73.49", "hundredth": "70.48", "last": "61.90", "top10avg": "75.58", "top25avg": "74.60", "top100avg": "72.47"},
{"yr": "2015", "statcode": "328", "statkey": "2015328", "stat": "gir-150-175", "heading": "GIR Percentage - 150-175 yards", "first": "73.87", "tenth": "70.70", "twentyfifth": "68.16", "hundredth": "63.95", "last": "55.56", "top10avg": "72.35", "top25avg": "70.35", "top100avg": "67.08"},
{"yr": "2015", "statcode": "326", "statkey": "2015326", "stat": "gir-200-plus", "heading": "GIR Percentage - 200+ yards", "first": "63.51", "tenth": "55.91", "twentyfifth": "52.29", "hundredth": "45.71", "last": "33.54", "top10avg": "58.15", "top25avg": "55.36", "top100avg": "50.07"},
{"yr": "2015", "statcode": "102", "statkey": "2015102", "stat": "driving", "heading": "Driving Accuracy Percentage", "first": "76.88", "tenth": "70.24", "twentyfifth": "67.87", "hundredth": "60.97", "last": "50.29", "top10avg": "72.11", "top25avg": "70.17", "top100avg": "65.67"},
{"yr": "2015", "statcode": "103", "statkey": "2015103", "stat": "gir", "heading": "Greens in Regulation Percentage", "first": "73.52", "tenth": "70.46", "twentyfifth": "68.99", "hundredth": "66.10", "last": "58.10", "top10avg": "71.83", "top25avg": "70.42", "top100avg": "68.19"},
{"yr": "2015", "statcode": "077", "statkey": "2015077", "stat": "gir-100-125", "heading": "GIR Percentage - 100-125 yards", "first": "86.13", "tenth": "82.96", "twentyfifth": "80.85", "hundredth": "75.77", "last": "60.00", "top10avg": "84.36", "top25avg": "82.73", "top100avg": "79.23"},
{"yr": "2015", "statcode": "111", "statkey": "2015111", "stat": "sand-saves", "heading": "Sand Save Percentage", "first": "63.19", "tenth": "61.11", "twentyfifth": "57.94", "hundredth": "50.00", "last": "37.17", "top10avg": "62.24", "top25avg": "60.62", "top100avg": "54.92"},
{"yr": "2015", "statcode": "419", "statkey": "2015419", "stat": "going-for-green", "heading": "Going for the Green", "first": "76.28", "tenth": "65.13", "twentyfifth": "60.39", "hundredth": "49.26", "last": "18.99", "top10avg": "68.32", "top25avg": "64.61", "top100avg": "57.01"},
{"yr": "2015", "statcode": "327", "statkey": "2015327", "stat": "gir-175-200", "heading": "GIR Percentage - 175-200 yards", "first": "67.11", "tenth": "63.22", "twentyfifth": "60.58", "hundredth": "55.74", "last": "44.30", "top10avg": "64.36", "top25avg": "62.97", "top100avg": "59.25"},
{"yr": "2015", "statcode": "130", "statkey": "2015130", "stat": "scrambling", "heading": "Scrambling", "first": "66.18", "tenth": "64.17", "twentyfifth": "62.24", "hundredth": "58.74", "last": "48.77", "top10avg": "64.89", "top25avg": "63.80", "top100avg": "61.24"},
{"yr": "2015", "statcode": "364", "statkey": "2015364", "stat": "scrambling-from-fringe", "heading": "Scrambling from the Fringe", "first": "100.00", "tenth": "95.56", "twentyfifth": "93.94", "hundredth": "89.66", "last": "75.68", "top10avg": "97.06", "top25avg": "95.55", "top100avg": "92.55"},
{"yr": "2015", "statcode": "399", "statkey": "2015399", "stat": "2-putts-per-round", "heading": "2-Putts per Round", "first": "11.49", "tenth": "10.85", "twentyfifth": "10.66", "hundredth": "10.16", "last": "9.27", "top10avg": "11.11", "top25avg": "10.91", "top100avg": "10.49"},
{"yr": "2015", "statcode": "119", "statkey": "2015119", "stat": "putts-per-round", "heading": "Putts Per Round", "first": "27.82", "tenth": "28.31", "twentyfifth": "28.51", "hundredth": "29.10", "last": "30.54", "top10avg": "28.21", "top25avg": "28.33", "top100avg": "28.70"},
{"yr": "2015", "statcode": "398", "statkey": "2015398", "stat": "1-putts-per-round", "heading": "1-Putts per Round", "first": "7.97", "tenth": "7.67", "twentyfifth": "7.46", "hundredth": "7.03", "last": "5.90", "top10avg": "7.75", "top25avg": "7.63", "top100avg": "7.33"},
{"yr": "2015", "statcode": "400", "statkey": "2015400", "stat": "3-putts-per-round", "heading": "3-Putts per Round", "first": ".92", "tenth": ".73", "twentyfifth": ".66", "hundredth": ".51", "last": ".30", "top10avg": "0.78", "top25avg": "0.73", "top100avg": "0.61"},
{"yr": "2015", "statcode": "403", "statkey": "2015403", "stat": "putting-inside-5", "heading": "Putting from Inside 5'", "first": "98.41", "tenth": "97.74", "twentyfifth": "97.46", "hundredth": "96.63", "last": "91.78", "top10avg": "98.03", "top25avg": "97.76", "top100avg": "97.19"},
{"yr": "2016", "statcode": "102", "statkey": "2016102", "stat": "driving", "heading": "Driving Accuracy Percentage", "first": "73.36", "tenth": "68.22", "twentyfifth": "65.59", "hundredth": "59.47", "last": "43.02", "top10avg": "70.13", "top25avg": "68.06", "top100avg": "63.86"},
{"yr": "2016", "statcode": "329", "statkey": "2016329", "stat": "gir-125-150", "heading": "GIR Percentage - 125-150 yards", "first": "83.44", "tenth": "77.51", "twentyfifth": "75.56", "hundredth": "70.62", "last": "59.90", "top10avg": "79.56", "top25avg": "77.67", "top100avg": "74.10"},
{"yr": "2016", "statcode": "077", "statkey": "2016077", "stat": "gir-100-125", "heading": "GIR Percentage - 100-125 yards", "first": "85.86", "tenth": "82.42", "twentyfifth": "80.33", "hundredth": "74.29", "last": "61.11", "top10avg": "83.77", "top25avg": "82.28", "top100avg": "78.13"},
{"yr": "2016", "statcode": "103", "statkey": "2016103", "stat": "gir", "heading": "Greens in Regulation Percentage", "first": "71.63", "tenth": "69.71", "twentyfifth": "68.72", "hundredth": "65.31", "last": "54.23", "top10avg": "70.33", "top25avg": "69.60", "top100avg": "67.55"},
{"yr": "2015", "statcode": "484", "statkey": "2015484", "stat": "putting-inside-10", "heading": "Putting - Inside 10'", "first": "90.39", "tenth": "89.39", "twentyfifth": "88.79", "hundredth": "87.49", "last": "83.42", "top10avg": "89.68", "top25avg": "89.27", "top100avg": "88.39"},
{"yr": "2016", "statcode": "02437", "statkey": "201602437", "stat": "GOFIR", "heading": "Greens or Fringe in Regulation", "first": "76.69", "tenth": "74.01", "twentyfifth": "72.93", "hundredth": "69.56", "last": "58.13", "top10avg": "74.61", "top25avg": "73.96", "top100avg": "71.89"},
{"yr": "2016", "statcode": "328", "statkey": "2016328", "stat": "gir-150-175", "heading": "GIR Percentage - 150-175 yards", "first": "73.20", "tenth": "70.51", "twentyfifth": "68.50", "hundredth": "63.49", "last": "51.50", "top10avg": "71.38", "top25avg": "70.02", "top100avg": "66.89"},
{"yr": "2016", "statcode": "327", "statkey": "2016327", "stat": "gir-175-200", "heading": "GIR Percentage - 175-200 yards", "first": "66.48", "tenth": "61.79", "twentyfifth": "59.66", "hundredth": "55.11", "last": "40.40", "top10avg": "63.59", "top25avg": "61.86", "top100avg": "58.11"},
{"yr": "2016", "statcode": "419", "statkey": "2016419", "stat": "going-for-green", "heading": "Going for the Green", "first": "80.18", "tenth": "69.26", "twentyfifth": "63.43", "hundredth": "50.66", "last": "20.62", "top10avg": "72.84", "top25avg": "68.63", "top100avg": "59.23"},
{"yr": "2016", "statcode": "326", "statkey": "2016326", "stat": "gir-200-plus", "heading": "GIR Percentage - 200+ yards", "first": "60.15", "tenth": "55.93", "twentyfifth": "52.49", "hundredth": "45.09", "last": "25.87", "top10avg": "57.85", "top25avg": "55.54", "top100avg": "50.37"},
{"yr": "2016", "statcode": "130", "statkey": "2016130", "stat": "scrambling", "heading": "Scrambling", "first": "66.01", "tenth": "63.66", "twentyfifth": "62.09", "hundredth": "58.18", "last": "49.14", "top10avg": "64.48", "top25avg": "63.38", "top100avg": "60.85"},
{"yr": "2016", "statcode": "111", "statkey": "2016111", "stat": "sand-saves", "heading": "Sand Save Percentage", "first": "62.42", "tenth": "58.96", "twentyfifth": "56.57", "hundredth": "49.09", "last": "38.20", "top10avg": "60.67", "top25avg": "58.67", "top100avg": "54.15"},
{"yr": "2016", "statcode": "364", "statkey": "2016364", "stat": "scrambling-from-fringe", "heading": "Scrambling from the Fringe", "first": "100.00", "tenth": "96.00", "twentyfifth": "94.34", "hundredth": "89.23", "last": "75.81", "top10avg": "97.64", "top25avg": "96.13", "top100avg": "92.73"},
{"yr": "2016", "statcode": "398", "statkey": "2016398", "stat": "1-putts-per-round", "heading": "1-Putts per Round", "first": "8.06", "tenth": "7.69", "twentyfifth": "7.45", "hundredth": "6.95", "last": "5.71", "top10avg": "7.86", "top25avg": "7.66", "top100avg": "7.30"},
{"yr": "2016", "statcode": "119", "statkey": "2016119", "stat": "putts-per-round", "heading": "Putts Per Round", "first": "27.82", "tenth": "28.28", "twentyfifth": "28.54", "hundredth": "29.17", "last": "30.45", "top10avg": "28.04", "top25avg": "28.28", "top100avg": "28.74"},
{"yr": "2016", "statcode": "399", "statkey": "2016399", "stat": "2-putts-per-round", "heading": "2-Putts per Round", "first": "11.55", "tenth": "10.80", "twentyfifth": "10.64", "hundredth": "10.19", "last": "9.30", "top10avg": "11.05", "top25avg": "10.85", "top100avg": "10.53"},
{"yr": "2017", "statcode": "103", "statkey": "2017103", "stat": "gir", "heading": "Greens in Regulation Percentage", "first": "70.64", "tenth": "69.52", "twentyfifth": "68.19", "hundredth": "65.60", "last": "53.54", "top10avg": "69.98", "top25avg": "69.28", "top100avg": "67.29"},
{"yr": "2016", "statcode": "484", "statkey": "2016484", "stat": "putting-inside-10", "heading": "Putting - Inside 10'", "first": "90.30", "tenth": "89.16", "twentyfifth": "88.77", "hundredth": "87.41", "last": "83.33", "top10avg": "89.75", "top25avg": "89.23", "top100avg": "88.33"},
{"yr": "2016", "statcode": "400", "statkey": "2016400", "stat": "3-putts-per-round", "heading": "3-Putts per Round", "first": ".80", "tenth": ".70", "twentyfifth": ".65", "hundredth": ".50", "last": ".25", "top10avg": "0.74", "top25avg": "0.70", "top100avg": "0.60"},
{"yr": "2016", "statcode": "403", "statkey": "2016403", "stat": "putting-inside-5", "heading": "Putting from Inside 5'", "first": "98.57", "tenth": "97.78", "twentyfifth": "97.44", "hundredth": "96.57", "last": "93.84", "top10avg": "98.07", "top25avg": "97.80", "top100avg": "97.18"},
{"yr": "2017", "statcode": "102", "statkey": "2017102", "stat": "driving", "heading": "Driving Accuracy Percentage", "first": "72.73", "tenth": "69.15", "twentyfifth": "66.54", "hundredth": "59.83", "last": "45.37", "top10avg": "70.51", "top25avg": "68.83", "top100avg": "64.38"},
{"yr": "2017", "statcode": "02437", "statkey": "201702437", "stat": "GOFIR", "heading": "Greens or Fringe in Regulation", "first": "74.66", "tenth": "72.86", "twentyfifth": "71.73", "hundredth": "68.58", "last": "56.79", "top10avg": "73.65", "top25avg": "72.75", "top100avg": "70.72"},
{"yr": "2017", "statcode": "077", "statkey": "2017077", "stat": "gir-100-125", "heading": "GIR Percentage - 100-125 yards", "first": "85.43", "tenth": "81.58", "twentyfifth": "80.00", "hundredth": "74.44", "last": "55.56", "top10avg": "83.48", "top25avg": "81.77", "top100avg": "78.18"},
{"yr": "2017", "statcode": "329", "statkey": "2017329", "stat": "gir-125-150", "heading": "GIR Percentage - 125-150 yards", "first": "78.15", "tenth": "75.97", "twentyfifth": "73.42", "hundredth": "68.35", "last": "54.29", "top10avg": "77.27", "top25avg": "75.65", "top100avg": "71.90"},
{"yr": "2017", "statcode": "328", "statkey": "2017328", "stat": "gir-150-175", "heading": "GIR Percentage - 150-175 yards", "first": "71.97", "tenth": "69.81", "twentyfifth": "67.87", "hundredth": "62.75", "last": "50.28", "top10avg": "70.76", "top25avg": "69.66", "top100avg": "66.43"},
{"yr": "2017", "statcode": "327", "statkey": "2017327", "stat": "gir-175-200", "heading": "GIR Percentage - 175-200 yards", "first": "68.03", "tenth": "62.72", "twentyfifth": "60.42", "hundredth": "55.26", "last": "44.25", "top10avg": "64.57", "top25avg": "62.87", "top100avg": "59.00"},
{"yr": "2017", "statcode": "111", "statkey": "2017111", "stat": "sand-saves", "heading": "Sand Save Percentage", "first": "67.69", "tenth": "60.42", "twentyfifth": "57.14", "hundredth": "50.43", "last": "36.43", "top10avg": "62.51", "top25avg": "59.86", "top100avg": "54.92"},
{"yr": "2017", "statcode": "326", "statkey": "2017326", "stat": "gir-200-plus", "heading": "GIR Percentage - 200+ yards", "first": "60.68", "tenth": "53.45", "twentyfifth": "51.82", "hundredth": "44.30", "last": "26.79", "top10avg": "55.95", "top25avg": "53.86", "top100avg": "49.45"},
{"yr": "2017", "statcode": "419", "statkey": "2017419", "stat": "going-for-green", "heading": "Going for the Green", "first": "73.50", "tenth": "67.35", "twentyfifth": "63.40", "hundredth": "52.49", "last": "26.58", "top10avg": "70.06", "top25avg": "67.00", "top100avg": "59.48"},
{"yr": "2017", "statcode": "130", "statkey": "2017130", "stat": "scrambling", "heading": "Scrambling", "first": "67.36", "tenth": "63.65", "twentyfifth": "62.74", "hundredth": "58.74", "last": "48.01", "top10avg": "64.87", "top25avg": "63.81", "top100avg": "61.19"},
{"yr": "2017", "statcode": "119", "statkey": "2017119", "stat": "putts-per-round", "heading": "Putts Per Round", "first": "28.12", "tenth": "28.30", "twentyfifth": "28.49", "hundredth": "29.09", "last": "30.42", "top10avg": "28.20", "top25avg": "28.31", "top100avg": "28.69"},
{"yr": "2017", "statcode": "364", "statkey": "2017364", "stat": "scrambling-from-fringe", "heading": "Scrambling from the Fringe", "first": "100.00", "tenth": "97.62", "twentyfifth": "95.74", "hundredth": "89.74", "last": "71.43", "top10avg": "99.14", "top25avg": "97.55", "top100avg": "93.59"},
{"yr": "2017", "statcode": "398", "statkey": "2017398", "stat": "1-putts-per-round", "heading": "1-Putts per Round", "first": "7.89", "tenth": "7.57", "twentyfifth": "7.39", "hundredth": "6.88", "last": "5.91", "top10avg": "7.67", "top25avg": "7.55", "top100avg": "7.23"},
{"yr": "2017", "statcode": "400", "statkey": "2017400", "stat": "3-putts-per-round", "heading": "3-Putts per Round", "first": ".89", "tenth": ".71", "twentyfifth": ".65", "hundredth": ".51", "last": ".24", "top10avg": "0.77", "top25avg": "0.71", "top100avg": "0.60"},
{"yr": "2017", "statcode": "399", "statkey": "2017399", "stat": "2-putts-per-round", "heading": "2-Putts per Round", "first": "11.44", "tenth": "10.74", "twentyfifth": "10.51", "hundredth": "9.98", "last": "8.89", "top10avg": "10.92", "top25avg": "10.73", "top100avg": "10.35"},
{"yr": "2017", "statcode": "484", "statkey": "2017484", "stat": "putting-inside-10", "heading": "Putting - Inside 10'", "first": "90.32", "tenth": "89.12", "twentyfifth": "88.58", "hundredth": "87.33", "last": "83.90", "top10avg": "89.52", "top25avg": "89.09", "top100avg": "88.23"},
{"yr": "2017", "statcode": "403", "statkey": "2017403", "stat": "putting-inside-5", "heading": "Putting from Inside 5'", "first": "98.20", "tenth": "97.92", "twentyfifth": "97.48", "hundredth": "96.58", "last": "93.92", "top10avg": "98.04", "top25avg": "97.81", "top100avg": "97.20"},
{"yr": "2018", "statcode": "102", "statkey": "2018102", "stat": "driving", "heading": "Driving Accuracy Percentage", "first": "75.19", "tenth": "69.91", "twentyfifth": "66.74", "hundredth": "61.53", "last": "47.15", "top10avg": "71.72", "top25avg": "69.38", "top100avg": "65.37"},
{"yr": "2018", "statcode": "077", "statkey": "2018077", "stat": "gir-100-125", "heading": "GIR Percentage - 100-125 yards", "first": "87.02", "tenth": "84.40", "twentyfifth": "81.44", "hundredth": "76.00", "last": "63.46", "top10avg": "85.30", "top25avg": "83.63", "top100avg": "79.72"},
{"yr": "2018", "statcode": "329", "statkey": "2018329", "stat": "gir-125-150", "heading": "GIR Percentage - 125-150 yards", "first": "80.43", "tenth": "76.92", "twentyfifth": "75.51", "hundredth": "71.27", "last": "58.11", "top10avg": "78.28", "top25avg": "76.95", "top100avg": "74.13"},
{"yr": "2018", "statcode": "103", "statkey": "2018103", "stat": "gir", "heading": "Greens in Regulation Percentage", "first": "73.51", "tenth": "70.52", "twentyfifth": "69.65", "hundredth": "66.51", "last": "56.79", "top10avg": "71.36", "top25avg": "70.64", "top100avg": "68.70"},
{"yr": "2018", "statcode": "02437", "statkey": "201802437", "stat": "GOFIR", "heading": "Greens or Fringe in Regulation", "first": "77.40", "tenth": "73.71", "twentyfifth": "72.95", "hundredth": "69.85", "last": "57.75", "top10avg": "74.75", "top25avg": "73.84", "top100avg": "71.89"},
{"yr": "2018", "statcode": "327", "statkey": "2018327", "stat": "gir-175-200", "heading": "GIR Percentage - 175-200 yards", "first": "67.54", "tenth": "63.60", "twentyfifth": "60.71", "hundredth": "55.50", "last": "41.98", "top10avg": "64.70", "top25avg": "63.00", "top100avg": "59.08"},
{"yr": "2018", "statcode": "419", "statkey": "2018419", "stat": "going-for-green", "heading": "Going for the Green", "first": "78.45", "tenth": "71.63", "twentyfifth": "67.01", "hundredth": "56.52", "last": "27.97", "top10avg": "73.77", "top25avg": "70.69", "top100avg": "62.98"},
{"yr": "2018", "statcode": "328", "statkey": "2018328", "stat": "gir-150-175", "heading": "GIR Percentage - 150-175 yards", "first": "74.12", "tenth": "71.49", "twentyfifth": "69.21", "hundredth": "64.19", "last": "46.98", "top10avg": "72.62", "top25avg": "71.26", "top100avg": "67.52"},
{"yr": "2018", "statcode": "111", "statkey": "2018111", "stat": "sand-saves", "heading": "Sand Save Percentage", "first": "66.00", "tenth": "60.81", "twentyfifth": "56.52", "hundredth": "49.23", "last": "32.43", "top10avg": "62.35", "top25avg": "59.74", "top100avg": "54.14"},
{"yr": "2018", "statcode": "326", "statkey": "2018326", "stat": "gir-200-plus", "heading": "GIR Percentage - 200+ yards", "first": "63.08", "tenth": "55.88", "twentyfifth": "52.41", "hundredth": "46.23", "last": "31.71", "top10avg": "58.52", "top25avg": "55.82", "top100avg": "50.63"},
{"yr": "2018", "statcode": "130", "statkey": "2018130", "stat": "scrambling", "heading": "Scrambling", "first": "66.10", "tenth": "63.53", "twentyfifth": "62.35", "hundredth": "57.94", "last": "44.01", "top10avg": "64.26", "top25avg": "63.42", "top100avg": "60.73"},
{"yr": "2018", "statcode": "364", "statkey": "2018364", "stat": "scrambling-from-fringe", "heading": "Scrambling from the Fringe", "first": "100.00", "tenth": "97.44", "twentyfifth": "96.43", "hundredth": "90.20", "last": "71.43", "top10avg": "99.01", "top25avg": "97.76", "top100avg": "94.46"},
{"yr": "2018", "statcode": "398", "statkey": "2018398", "stat": "1-putts-per-round", "heading": "1-Putts per Round", "first": "7.96", "tenth": "7.66", "twentyfifth": "7.44", "hundredth": "6.96", "last": "5.96", "top10avg": "7.75", "top25avg": "7.60", "top100avg": "7.26"},
{"yr": "2018", "statcode": "119", "statkey": "2018119", "stat": "putts-per-round", "heading": "Putts Per Round", "first": "27.82", "tenth": "28.31", "twentyfifth": "28.52", "hundredth": "29.15", "last": "30.37", "top10avg": "28.14", "top25avg": "28.32", "top100avg": "28.76"},
{"yr": "2018", "statcode": "399", "statkey": "2018399", "stat": "2-putts-per-round", "heading": "2-Putts per Round", "first": "11.32", "tenth": "10.88", "twentyfifth": "10.69", "hundredth": "10.28", "last": "9.39", "top10avg": "11.05", "top25avg": "10.88", "top100avg": "10.57"},
{"yr": "2018", "statcode": "400", "statkey": "2018400", "stat": "3-putts-per-round", "heading": "3-Putts per Round", "first": ".98", "tenth": ".75", "twentyfifth": ".66", "hundredth": ".51", "last": ".27", "top10avg": "0.81", "top25avg": "0.74", "top100avg": "0.61"},
{"yr": "2018", "statcode": "484", "statkey": "2018484", "stat": "putting-inside-10", "heading": "Putting - Inside 10'", "first": "91.18", "tenth": "89.45", "twentyfifth": "88.90", "hundredth": "87.51", "last": "84.08", "top10avg": "89.86", "top25avg": "89.44", "top100avg": "88.40"},
{"yr": "2018", "statcode": "403", "statkey": "2018403", "stat": "putting-inside-5", "heading": "Putting from Inside 5'", "first": "98.65", "tenth": "97.93", "twentyfifth": "97.63", "hundredth": "96.78", "last": "94.54", "top10avg": "98.19", "top25avg": "97.95", "top100avg": "97.38"},
{"yr": "2019", "statcode": "102", "statkey": "2019102", "stat": "driving", "heading": "Driving Accuracy Percentage", "first": "81.72", "tenth": "70.75", "twentyfifth": "68.40", "hundredth": "61.75", "last": "46.22", "top10avg": "73.20", "top25avg": "70.91", "top100avg": "66.57"},
{"yr": "2019", "statcode": "02437", "statkey": "201902437", "stat": "GOFIR", "heading": "Greens or Fringe in Regulation", "first": "79.24", "tenth": "76.62", "twentyfifth": "74.32", "hundredth": "70.44", "last": "59.60", "top10avg": "77.87", "top25avg": "76.36", "top100avg": "73.20"},
{"yr": "2019", "statcode": "077", "statkey": "2019077", "stat": "gir-100-125", "heading": "GIR Percentage - 100-125 yards", "first": "96.55", "tenth": "89.80", "twentyfifth": "84.21", "hundredth": "76.83", "last": "25.00", "top10avg": "92.47", "top25avg": "89.08", "top100avg": "82.71"},
{"yr": "2019", "statcode": "329", "statkey": "2019329", "stat": "gir-125-150", "heading": "GIR Percentage - 125-150 yards", "first": "92.50", "tenth": "81.03", "twentyfifth": "77.19", "hundredth": "70.45", "last": "44.12", "top10avg": "84.15", "top25avg": "81.15", "top100avg": "75.41"},
{"yr": "2019", "statcode": "103", "statkey": "2019103", "stat": "gir", "heading": "Greens in Regulation Percentage", "first": "76.19", "tenth": "73.33", "twentyfifth": "71.67", "hundredth": "68.18", "last": "57.00", "top10avg": "74.27", "top25avg": "73.09", "top100avg": "70.61"},
{"yr": "2019", "statcode": "111", "statkey": "2019111", "stat": "sand-saves", "heading": "Sand Save Percentage", "first": "75.76", "tenth": "65.63", "twentyfifth": "61.29", "hundredth": "52.17", "last": "26.92", "top10avg": "70.64", "top25avg": "65.90", "top100avg": "58.28"},
{"yr": "2019", "statcode": "326", "statkey": "2019326", "stat": "gir-200-plus", "heading": "GIR Percentage - 200+ yards", "first": "71.88", "tenth": "60.53", "twentyfifth": "56.00", "hundredth": "45.95", "last": "18.18", "top10avg": "65.41", "top25avg": "61.13", "top100avg": "52.75"},
{"yr": "2019", "statcode": "419", "statkey": "2019419", "stat": "going-for-green", "heading": "Going for the Green", "first": "80.95", "tenth": "76.84", "twentyfifth": "71.76", "hundredth": "60.64", "last": "24.39", "top10avg": "78.53", "top25avg": "75.65", "top100avg": "68.03"},
{"yr": "2019", "statcode": "328", "statkey": "2019328", "stat": "gir-150-175", "heading": "GIR Percentage - 150-175 yards", "first": "85.71", "tenth": "75.56", "twentyfifth": "72.73", "hundredth": "66.29", "last": "40.51", "top10avg": "77.94", "top25avg": "75.48", "top100avg": "70.78"},
{"yr": "2019", "statcode": "327", "statkey": "2019327", "stat": "gir-175-200", "heading": "GIR Percentage - 175-200 yards", "first": "77.78", "tenth": "68.33", "twentyfifth": "65.38", "hundredth": "56.52", "last": "33.33", "top10avg": "70.60", "top25avg": "68.27", "top100avg": "62.38"},
{"yr": "2019", "statcode": "398", "statkey": "2019398", "stat": "1-putts-per-round", "heading": "1-Putts per Round", "first": "8.50", "tenth": "7.84", "twentyfifth": "7.66", "hundredth": "7.00", "last": "5.89", "top10avg": "8.05", "top25avg": "7.86", "top100avg": "7.43"},
{"yr": "2019", "statcode": "364", "statkey": "2019364", "stat": "scrambling-from-fringe", "heading": "Scrambling from the Fringe", "first": "100.00", "tenth": "100.00", "twentyfifth": "100.00", "hundredth": "90.91", "last": "33.33", "top10avg": "100.00", "top25avg": "100.00", "top100avg": "97.88"},
{"yr": "2019", "statcode": "130", "statkey": "2019130", "stat": "scrambling", "heading": "Scrambling", "first": "71.97", "tenth": "67.15", "twentyfifth": "65.26", "hundredth": "60.66", "last": "46.60", "top10avg": "69.00", "top25avg": "67.27", "top100avg": "63.84"},
{"yr": "2019", "statcode": "119", "statkey": "2019119", "stat": "putts-per-round", "heading": "Putts Per Round", "first": "27.19", "tenth": "28.09", "twentyfifth": "28.41", "hundredth": "29.05", "last": "30.63", "top10avg": "27.82", "top25avg": "28.12", "top100avg": "28.61"},
{"yr": "2019", "statcode": "399", "statkey": "2019399", "stat": "2-putts-per-round", "heading": "2-Putts per Round", "first": "11.51", "tenth": "10.89", "twentyfifth": "10.73", "hundredth": "10.27", "last": "8.60", "top10avg": "11.09", "top25avg": "10.92", "top100avg": "10.58"},
{"yr": "2019", "statcode": "400", "statkey": "2019400", "stat": "3-putts-per-round", "heading": "3-Putts per Round", "first": "1.20", "tenth": ".85", "twentyfifth": ".74", "hundredth": ".57", "last": ".19", "top10avg": "0.96", "top25avg": "0.85", "top100avg": "0.69"},
{"yr": "2019", "statcode": "484", "statkey": "2019484", "stat": "putting-inside-10", "heading": "Putting - Inside 10'", "first": "92.74", "tenth": "90.23", "twentyfifth": "89.32", "hundredth": "87.72", "last": "75.41", "top10avg": "90.99", "top25avg": "90.17", "top100avg": "88.80"},
{"yr": "2019", "statcode": "403", "statkey": "2019403", "stat": "putting-inside-5", "heading": "Putting from Inside 5'", "first": "99.40", "tenth": "98.48", "twentyfifth": "97.99", "hundredth": "96.46", "last": "84.00", "top10avg": "98.77", "top25avg": "98.44", "top100avg": "97.49"}
]